{"gameId":4723521434,"participantIdentities":[{"participantId":1,"player":{"profileIcon":4540,"accountId":"bPXEkVDbb9yH9pzCzyyYrAz_9P4NTb8gp3CsMOXoukvK2A","matchHistoryUri":"\/v1\/stats\/player_history\/EUW1\/41779990","currentAccountId":"bPXEkVDbb9yH9pzCzyyYrAz_9P4NTb8gp3CsMOXoukvK2A","currentPlatformId":"EUW1","summonerName":"darkchri99","summonerId":"jJgoHjUVKnMe2-mXkd5mDSvAfdVrC2syUa3ie3qDSShbZyo","platformId":"EUW1"}},{"participantId":2,"player":{"profileIcon":4244,"accountId":"LLegnPKh8kczQRu6idCAIku2lasUwu5JJYe_N73avv3bfw","matchHistoryUri":"\/v1\/stats\/player_history\/EUW1\/36902634","currentAccountId":"LLegnPKh8kczQRu6idCAIku2lasUwu5JJYe_N73avv3bfw","currentPlatformId":"EUW1","summonerName":"ok nice cool","summonerId":"dmumCo9rmvKbOfW1tS4HUpa4dKLnbuukk3DNwpqllKvBb_Q","platformId":"EUW1"}},{"participantId":3,"player":{"profileIcon":982,"accountId":"aJ2-swrkQ9Slsy37SiL5iLjha6jFkOSSMJeAfs3NSHfxBVWgjFoeLgK1","matchHistoryUri":"\/v1\/stats\/player_history\/EUW1\/2253203745435808","currentAccountId":"aJ2-swrkQ9Slsy37SiL5iLjha6jFkOSSMJeAfs3NSHfxBVWgjFoeLgK1","currentPlatformId":"EUW1","summonerName":"Patrik1","summonerId":"FicAX0-yo7qbYxtOTsayRePkL0AWnEZeFEDs-eBxWKuZ8tQO","platformId":"EUW1"}},{"participantId":4,"player":{"profileIcon":4447,"accountId":"aD9tH2GSviAvi3fItwpvjQ43NHKJLhFl6aQmJRL03Rt66A","matchHistoryUri":"\/v1\/stats\/player_history\/EUW1\/23989840","currentAccountId":"aD9tH2GSviAvi3fItwpvjQ43NHKJLhFl6aQmJRL03Rt66A","currentPlatformId":"EUW1","summonerName":"Robert Chase","summonerId":"xJ6ahrc_VEtRUlNuCqOyR_pzwkFRqv7zJ8XoYIWIMsMLK8A","platformId":"EUW1"}},{"participantId":5,"player":{"profileIcon":4568,"accountId":"CqaUaoFqeheNIAY311gA-4oE-DrsJje0NhGbCygfEv8jpNTnSsDon_ih","matchHistoryUri":"\/v1\/stats\/player_history\/EUW1\/2427668322578624","currentAccountId":"CqaUaoFqeheNIAY311gA-4oE-DrsJje0NhGbCygfEv8jpNTnSsDon_ih","currentPlatformId":"EUW1","summonerName":"xLinayaa","summonerId":"b4WBK6_JWHUZchy3No48yDtcdP75hCHMwE_aC8sDz7KKAwyc","platformId":"EUW1"}},{"participantId":6,"player":{"profileIcon":4576,"accountId":"mYHU41MmIdizA6hunZa6nYI44bIQHUBjFa-NpgbA3RWO2EKOYXNZ7QsY","matchHistoryUri":"\/v1\/stats\/player_history\/EUW1\/2455958230928288","currentAccountId":"mYHU41MmIdizA6hunZa6nYI44bIQHUBjFa-NpgbA3RWO2EKOYXNZ7QsY","currentPlatformId":"EUW1","summonerName":"EU Kanavi","summonerId":"_Yx5dlcbWQAQS9yYAs3suiTmOuEnFgtlIpAibLn_pdIQfM6L","platformId":"EUW1"}},{"participantId":7,"player":{"profileIcon":22,"accountId":"IYFQAT98yJaKJfHra3HVo4naOIvwCFZm6fmjBmvUURjZBw","matchHistoryUri":"\/v1\/stats\/player_history\/EUW1\/31885574","currentAccountId":"IYFQAT98yJaKJfHra3HVo4naOIvwCFZm6fmjBmvUURjZBw","currentPlatformId":"EUW1","summonerName":"SLY Tønerre","summonerId":"fMhGNISv_-d9AacgbpgPpasP2rrs29KlPTBNH_0mQLukjQ8","platformId":"EUW1"}},{"participantId":8,"player":{"profileIcon":4607,"accountId":"X8yIKYvHZVtmRG8ddYlNFXNlpDl4urbESR5_QsNoSJuJhw","matchHistoryUri":"\/v1\/stats\/player_history\/EUW1\/22831284","currentAccountId":"X8yIKYvHZVtmRG8ddYlNFXNlpDl4urbESR5_QsNoSJuJhw","currentPlatformId":"EUW1","summonerName":"Asi es JaVaaa ","summonerId":"9fVIj_C6knI_r5PQoffPmn2JMm0IDwswPQvVcNDZZ8i2_wQ","platformId":"EUW1"}},{"participantId":9,"player":{"profileIcon":4561,"accountId":"LbC5NSWimCfin5OX8ivTe8mdBTxZ_--tmfDIKb8T4TAvmMk","matchHistoryUri":"\/v1\/stats\/player_history\/EUW1\/201329542","currentAccountId":"LbC5NSWimCfin5OX8ivTe8mdBTxZ_--tmfDIKb8T4TAvmMk","currentPlatformId":"EUW1","summonerName":"MRS Make","summonerId":"jQpVY3ReEqRRny2PPm3RREKqOxr-zoBCGC_6CxpV_3yTdzU","platformId":"EUW1"}},{"participantId":10,"player":{"profileIcon":4353,"accountId":"cymSWsJay-0JHD3UDBO9_e6WSSTZcBm2_DF-MPWuNVoAUQ","matchHistoryUri":"\/v1\/stats\/player_history\/EUW1\/31145123","currentAccountId":"cymSWsJay-0JHD3UDBO9_e6WSSTZcBm2_DF-MPWuNVoAUQ","currentPlatformId":"EUW1","summonerName":"Agurin","summonerId":"KID8DNt9DMSUatFZeOGkCFcyXyqkqLy1eHvi0UmPgJR9qlU","platformId":"EUW1"}}],"queueId":420,"gameType":"MATCHED_GAME","gameDuration":1802,"teams":[{"towerKills":7,"riftHeraldKills":2,"firstBlood":false,"inhibitorKills":2,"bans":[{"championId":-1,"pickTurn":1},{"championId":98,"pickTurn":2},{"championId":432,"pickTurn":3},{"championId":876,"pickTurn":4},{"championId":53,"pickTurn":5}],"firstBaron":true,"firstDragon":false,"dominionVictoryScore":0,"dragonKills":2,"baronKills":1,"firstInhibitor":true,"firstTower":true,"vilemawKills":0,"firstRiftHerald":true,"teamId":100,"win":"Win"},{"towerKills":5,"riftHeraldKills":0,"firstBlood":true,"inhibitorKills":0,"bans":[{"championId":142,"pickTurn":6},{"championId":53,"pickTurn":7},{"championId":412,"pickTurn":8},{"championId":4,"pickTurn":9},{"championId":64,"pickTurn":10}],"firstBaron":false,"firstDragon":true,"dominionVictoryScore":0,"dragonKills":1,"baronKills":0,"firstInhibitor":false,"firstTower":false,"vilemawKills":0,"firstRiftHerald":false,"teamId":200,"win":"Fail"}],"platformId":"EUW1","gameCreation":1595587527121,"seasonId":13,"gameVersion":"10.15.328.8759","mapId":11,"gameMode":"CLASSIC","participants":[{"participantId":1,"championId":350,"stats":{"totalUnitsHealed":5,"largestMultiKill":1,"firstInhibitorKill":false,"totalPlayerScore":0,"damageDealtToObjectives":3142,"playerScore0":0,"deaths":2,"magicDamageDealtToChampions":8778,"wardsKilled":0,"playerScore7":0,"perkSubStyle":8000,"playerScore8":0,"pentaKills":0,"playerScore5":0,"playerScore6":0,"playerScore3":0,"playerScore4":0,"playerScore1":0,"totalTimeCrowdControlDealt":51,"playerScore2":0,"firstTowerKill":false,"playerScore9":0,"perk1Var3":0,"perk1Var2":915,"totalScoreRank":0,"perk1Var1":250,"wardsPlaced":26,"totalDamageDealt":18048,"largestKillingSpree":0,"totalDamageDealtToChampions":9809,"neutralMinionsKilledTeamJungle":0,"firstInhibitorAssist":false,"objectivePlayerScore":0,"inhibitorKills":0,"perk3Var3":0,"perk3Var2":0,"participantId":1,"perk3Var1":48,"goldSpent":7700,"perk1":8226,"perk0":8214,"perk3":8236,"perk2":8210,"perk5":8017,"perk4":8009,"unrealKills":0,"perk5Var3":0,"perk5Var2":0,"visionScore":48,"perk5Var1":782,"firstBloodKill":false,"longestTimeSpentLiving":332,"killingSprees":0,"sightWardsBoughtInGame":0,"quadraKills":0,"item4":3114,"item3":3041,"item6":3364,"item5":2055,"perkPrimaryStyle":8200,"item0":3174,"item2":3853,"item1":3504,"statPerk1":5008,"statPerk0":5008,"goldEarned":8511,"physicalDamageTaken":3429,"champLevel":14,"totalDamageTaken":5620,"neutralMinionsKilled":0,"statPerk2":5002,"tripleKills":0,"damageSelfMitigated":4395,"largestCriticalStrike":0,"magicDamageDealt":15018,"timeCCingOthers":22,"magicalDamageTaken":2043,"physicalDamageDealtToChampions":1031,"perk0Var2":2721,"perk0Var1":1225,"totalMinionsKilled":3,"visionWardsBoughtInGame":8,"perk0Var3":0,"kills":2,"firstTowerAssist":false,"perk2Var2":0,"perk2Var1":0,"combatPlayerScore":0,"turretKills":0,"trueDamageTaken":147,"firstBloodAssist":false,"assists":16,"damageDealtToTurrets":1799,"win":true,"totalHeal":16858,"perk2Var3":0,"physicalDamageDealt":3030,"trueDamageDealtToChampions":0,"neutralMinionsKilledEnemyJungle":0,"doubleKills":0,"trueDamageDealt":0,"perk4Var2":500,"perk4Var1":5016,"perk4Var3":0},"teamId":100,"timeline":{"participantId":1,"damageTakenPerMinDeltas":{"10-20":252.9,"0-10":168,"20-30":141.1},"role":"DUO_SUPPORT","xpPerMinDeltas":{"10-20":382.70000000000005,"0-10":288.4,"20-30":589.8},"lane":"BOTTOM","creepsPerMinDeltas":{"10-20":0,"0-10":0.1,"20-30":0.2},"goldPerMinDeltas":{"10-20":298.6,"0-10":213.1,"20-30":288.9}},"spell1Id":7,"spell2Id":3},{"participantId":2,"championId":76,"stats":{"totalUnitsHealed":4,"largestMultiKill":1,"firstInhibitorKill":false,"totalPlayerScore":0,"damageDealtToObjectives":33056,"playerScore0":0,"deaths":6,"magicDamageDealtToChampions":8262,"wardsKilled":8,"playerScore7":0,"perkSubStyle":8200,"playerScore8":0,"pentaKills":0,"playerScore5":0,"playerScore6":0,"playerScore3":0,"playerScore4":0,"playerScore1":0,"totalTimeCrowdControlDealt":82,"playerScore2":0,"firstTowerKill":true,"playerScore9":0,"perk1Var3":0,"perk1Var2":0,"totalScoreRank":0,"perk1Var1":148,"wardsPlaced":16,"totalDamageDealt":172439,"largestKillingSpree":0,"totalDamageDealtToChampions":9547,"neutralMinionsKilledTeamJungle":85,"firstInhibitorAssist":false,"objectivePlayerScore":0,"inhibitorKills":0,"perk3Var3":0,"perk3Var2":4,"participantId":2,"perk3Var1":4497,"goldSpent":10400,"perk1":8143,"perk0":8112,"perk3":8135,"perk2":8136,"perk5":8232,"perk4":8275,"unrealKills":0,"perk5Var3":0,"perk5Var2":30,"visionScore":54,"perk5Var1":5,"firstBloodKill":false,"longestTimeSpentLiving":484,"killingSprees":0,"sightWardsBoughtInGame":0,"quadraKills":0,"item4":1082,"item3":3047,"item6":3364,"item5":1414,"perkPrimaryStyle":8100,"item0":3157,"item2":3174,"item1":1026,"statPerk1":5008,"statPerk0":5005,"goldEarned":10768,"physicalDamageTaken":18178,"champLevel":14,"totalDamageTaken":28639,"neutralMinionsKilled":142,"statPerk2":5002,"tripleKills":0,"damageSelfMitigated":15173,"largestCriticalStrike":0,"magicDamageDealt":130267,"timeCCingOthers":4,"magicalDamageTaken":9653,"physicalDamageDealtToChampions":772,"perk0Var2":0,"perk0Var1":464,"totalMinionsKilled":27,"visionWardsBoughtInGame":6,"perk0Var3":0,"kills":4,"firstTowerAssist":false,"perk2Var2":30,"perk2Var1":10,"combatPlayerScore":0,"turretKills":1,"trueDamageTaken":808,"firstBloodAssist":false,"assists":4,"damageDealtToTurrets":1521,"win":true,"totalHeal":19253,"perk2Var3":0,"physicalDamageDealt":24012,"trueDamageDealtToChampions":512,"neutralMinionsKilledEnemyJungle":18,"doubleKills":0,"trueDamageDealt":18158,"perk4Var2":0,"perk4Var1":21,"perk4Var3":0},"teamId":100,"timeline":{"participantId":2,"csDiffPerMinDeltas":{"10-20":0.19999999999999996,"0-10":0.3,"20-30":-0.6000000000000001},"damageTakenPerMinDeltas":{"10-20":1195.5,"0-10":794.3,"20-30":874.1},"role":"NONE","damageTakenDiffPerMinDeltas":{"10-20":350,"0-10":78.79999999999995,"20-30":-254.5999999999999},"xpPerMinDeltas":{"10-20":423.5,"0-10":320.2,"20-30":533.9},"xpDiffPerMinDeltas":{"10-20":-80,"0-10":-87.9,"20-30":127.69999999999999},"lane":"JUNGLE","creepsPerMinDeltas":{"10-20":0.6,"0-10":0.4,"20-30":1.7000000000000002},"goldPerMinDeltas":{"10-20":373.3,"0-10":297.8,"20-30":355.29999999999995}},"spell1Id":11,"spell2Id":4},{"participantId":3,"championId":246,"stats":{"totalUnitsHealed":1,"largestMultiKill":1,"firstInhibitorKill":false,"totalPlayerScore":0,"damageDealtToObjectives":230,"playerScore0":0,"deaths":4,"magicDamageDealtToChampions":1027,"wardsKilled":7,"playerScore7":0,"perkSubStyle":8300,"playerScore8":0,"pentaKills":0,"playerScore5":0,"playerScore6":0,"playerScore3":0,"playerScore4":0,"playerScore1":0,"totalTimeCrowdControlDealt":110,"playerScore2":0,"firstTowerKill":false,"playerScore9":0,"perk1Var3":0,"perk1Var2":0,"totalScoreRank":0,"perk1Var1":521,"wardsPlaced":14,"totalDamageDealt":99283,"largestKillingSpree":4,"totalDamageDealtToChampions":14976,"neutralMinionsKilledTeamJungle":0,"firstInhibitorAssist":false,"objectivePlayerScore":0,"inhibitorKills":0,"perk3Var3":0,"perk3Var2":0,"participantId":3,"perk3Var1":4,"goldSpent":8925,"perk1":8143,"perk0":8112,"perk3":8106,"perk2":8136,"perk5":8352,"perk4":8316,"unrealKills":0,"perk5Var3":873,"perk5Var2":1393,"visionScore":36,"perk5Var1":299,"firstBloodKill":false,"longestTimeSpentLiving":919,"killingSprees":2,"sightWardsBoughtInGame":0,"quadraKills":0,"item4":3133,"item3":3147,"item6":3364,"item5":1029,"perkPrimaryStyle":8100,"item0":3142,"item2":3117,"item1":2033,"statPerk1":5008,"statPerk0":5008,"goldEarned":11359,"physicalDamageTaken":10289,"champLevel":15,"totalDamageTaken":20128,"neutralMinionsKilled":8,"statPerk2":5003,"tripleKills":0,"damageSelfMitigated":9729,"largestCriticalStrike":0,"magicDamageDealt":5100,"timeCCingOthers":16,"magicalDamageTaken":9205,"physicalDamageDealtToChampions":13395,"perk0Var2":0,"perk0Var1":953,"totalMinionsKilled":164,"visionWardsBoughtInGame":3,"perk0Var3":0,"kills":8,"firstTowerAssist":false,"perk2Var2":14,"perk2Var1":7,"combatPlayerScore":0,"turretKills":0,"trueDamageTaken":633,"firstBloodAssist":false,"assists":6,"damageDealtToTurrets":230,"win":true,"totalHeal":2273,"perk2Var3":0,"physicalDamageDealt":92292,"trueDamageDealtToChampions":554,"neutralMinionsKilledEnemyJungle":4,"doubleKills":0,"trueDamageDealt":1890,"perk4Var2":0,"perk4Var1":3999,"perk4Var3":0},"teamId":100,"timeline":{"participantId":3,"csDiffPerMinDeltas":{"10-20":0,"0-10":-1.6999999999999995,"20-30":-5.5},"damageTakenPerMinDeltas":{"10-20":558.3,"0-10":443.9,"20-30":1010.5999999999999},"role":"SOLO","damageTakenDiffPerMinDeltas":{"10-20":-101.50000000000003,"0-10":81.79999999999998,"20-30":313.9},"xpPerMinDeltas":{"10-20":511.7,"0-10":354,"20-30":521.3},"xpDiffPerMinDeltas":{"10-20":139.89999999999998,"0-10":-125.60000000000002,"20-30":1.1000000000000227},"lane":"MIDDLE","creepsPerMinDeltas":{"10-20":6.4,"0-10":6.2,"20-30":3.8},"goldPerMinDeltas":{"10-20":413.4,"0-10":301.5,"20-30":370.6}},"spell1Id":4,"spell2Id":14},{"participantId":4,"championId":81,"stats":{"totalUnitsHealed":1,"largestMultiKill":3,"firstInhibitorKill":true,"totalPlayerScore":0,"damageDealtToObjectives":34748,"playerScore0":0,"deaths":3,"magicDamageDealtToChampions":9308,"wardsKilled":6,"playerScore7":0,"perkSubStyle":8300,"playerScore8":0,"pentaKills":0,"playerScore5":0,"playerScore6":0,"playerScore3":0,"playerScore4":0,"playerScore1":0,"totalTimeCrowdControlDealt":88,"playerScore2":0,"firstTowerKill":false,"playerScore9":0,"perk1Var3":0,"perk1Var2":500,"totalScoreRank":0,"perk1Var1":6762,"wardsPlaced":11,"totalDamageDealt":275920,"largestKillingSpree":6,"totalDamageDealtToChampions":27533,"neutralMinionsKilledTeamJungle":28,"firstInhibitorAssist":false,"objectivePlayerScore":0,"inhibitorKills":2,"perk3Var3":0,"perk3Var2":0,"participantId":4,"perk3Var1":553,"goldSpent":16108,"perk1":8009,"perk0":8010,"perk3":8014,"perk2":9103,"perk5":8347,"perk4":8345,"unrealKills":0,"perk5Var3":0,"perk5Var2":0,"visionScore":27,"perk5Var1":0,"firstBloodKill":false,"longestTimeSpentLiving":806,"killingSprees":2,"sightWardsBoughtInGame":0,"quadraKills":0,"item4":3078,"item3":3140,"item6":3363,"item5":3158,"perkPrimaryStyle":8000,"item0":3153,"item2":3812,"item1":3042,"statPerk1":5008,"statPerk0":5005,"goldEarned":17327,"physicalDamageTaken":14369,"champLevel":16,"totalDamageTaken":24511,"neutralMinionsKilled":55,"statPerk2":5002,"tripleKills":1,"damageSelfMitigated":14179,"largestCriticalStrike":0,"magicDamageDealt":37102,"timeCCingOthers":4,"magicalDamageTaken":8717,"physicalDamageDealtToChampions":17776,"perk0Var2":0,"perk0Var1":260,"totalMinionsKilled":262,"visionWardsBoughtInGame":3,"perk0Var3":0,"kills":10,"firstTowerAssist":false,"perk2Var2":10,"perk2Var1":22,"combatPlayerScore":0,"turretKills":5,"trueDamageTaken":1424,"firstBloodAssist":false,"assists":7,"damageDealtToTurrets":13211,"win":true,"totalHeal":2080,"perk2Var3":0,"physicalDamageDealt":235851,"trueDamageDealtToChampions":448,"neutralMinionsKilledEnemyJungle":19,"doubleKills":1,"trueDamageDealt":2966,"perk4Var2":0,"perk4Var1":3,"perk4Var3":0},"teamId":100,"timeline":{"participantId":4,"damageTakenPerMinDeltas":{"10-20":747.3,"0-10":432,"20-30":1271.8000000000002},"role":"DUO_CARRY","xpPerMinDeltas":{"10-20":475.5,"0-10":341,"20-30":749.6},"lane":"BOTTOM","creepsPerMinDeltas":{"10-20":9.2,"0-10":7.8999999999999995,"20-30":9.100000000000001},"goldPerMinDeltas":{"10-20":561.4000000000001,"0-10":330.79999999999995,"20-30":790.0999999999999}},"spell1Id":4,"spell2Id":21},{"participantId":5,"championId":85,"stats":{"totalUnitsHealed":1,"largestMultiKill":1,"firstInhibitorKill":false,"totalPlayerScore":0,"damageDealtToObjectives":3204,"playerScore0":0,"deaths":2,"magicDamageDealtToChampions":10328,"wardsKilled":3,"playerScore7":0,"perkSubStyle":8100,"playerScore8":0,"pentaKills":0,"playerScore5":0,"playerScore6":0,"playerScore3":0,"playerScore4":0,"playerScore1":0,"totalTimeCrowdControlDealt":60,"playerScore2":0,"firstTowerKill":false,"playerScore9":0,"perk1Var3":0,"perk1Var2":0,"totalScoreRank":0,"perk1Var1":12,"wardsPlaced":10,"totalDamageDealt":98757,"largestKillingSpree":2,"totalDamageDealtToChampions":14555,"neutralMinionsKilledTeamJungle":0,"firstInhibitorAssist":false,"objectivePlayerScore":0,"inhibitorKills":0,"perk3Var3":0,"perk3Var2":0,"participantId":5,"perk3Var1":0,"goldSpent":11745,"perk1":8304,"perk0":8360,"perk3":8347,"perk2":8316,"perk5":8135,"perk4":8139,"unrealKills":0,"perk5Var3":0,"perk5Var2":4,"visionScore":19,"perk5Var1":1550,"firstBloodKill":false,"longestTimeSpentLiving":639,"killingSprees":1,"sightWardsBoughtInGame":0,"quadraKills":0,"item4":0,"item3":3165,"item6":3340,"item5":1055,"perkPrimaryStyle":8300,"item0":3157,"item2":3152,"item1":3020,"statPerk1":5008,"statPerk0":5005,"goldEarned":10689,"physicalDamageTaken":10303,"champLevel":16,"totalDamageTaken":16941,"neutralMinionsKilled":0,"statPerk2":5003,"tripleKills":0,"damageSelfMitigated":9754,"largestCriticalStrike":0,"magicDamageDealt":67760,"timeCCingOthers":25,"magicalDamageTaken":6119,"physicalDamageDealtToChampions":4037,"perk0Var2":0,"perk0Var1":13,"totalMinionsKilled":198,"visionWardsBoughtInGame":0,"perk0Var3":0,"kills":2,"firstTowerAssist":false,"perk2Var2":0,"perk2Var1":4311,"combatPlayerScore":0,"turretKills":0,"trueDamageTaken":518,"firstBloodAssist":false,"assists":5,"damageDealtToTurrets":1321,"win":true,"totalHeal":3396,"perk2Var3":0,"physicalDamageDealt":29399,"trueDamageDealtToChampions":190,"neutralMinionsKilledEnemyJungle":0,"doubleKills":0,"trueDamageDealt":1597,"perk4Var2":0,"perk4Var1":758,"perk4Var3":0},"teamId":100,"timeline":{"participantId":5,"damageTakenPerMinDeltas":{"10-20":692.3,"0-10":335.4,"20-30":666.4},"role":"SOLO","xpPerMinDeltas":{"10-20":464.4,"0-10":456.1,"20-30":567.1},"lane":"TOP","creepsPerMinDeltas":{"10-20":7.8,"0-10":7.5,"20-30":4.5},"goldPerMinDeltas":{"10-20":363.4,"0-10":257.9,"20-30":397.2}},"spell1Id":4,"spell2Id":12},{"participantId":6,"championId":79,"stats":{"totalUnitsHealed":1,"largestMultiKill":1,"firstInhibitorKill":false,"totalPlayerScore":0,"damageDealtToObjectives":9663,"playerScore0":0,"deaths":3,"magicDamageDealtToChampions":14644,"wardsKilled":8,"playerScore7":0,"perkSubStyle":8300,"playerScore8":0,"pentaKills":0,"playerScore5":0,"playerScore6":0,"playerScore3":0,"playerScore4":0,"playerScore1":0,"totalTimeCrowdControlDealt":607,"playerScore2":0,"firstTowerKill":false,"playerScore9":0,"perk1Var3":0,"perk1Var2":0,"totalScoreRank":0,"perk1Var1":462,"wardsPlaced":8,"totalDamageDealt":185383,"largestKillingSpree":3,"totalDamageDealtToChampions":16691,"neutralMinionsKilledTeamJungle":107,"firstInhibitorAssist":false,"objectivePlayerScore":0,"inhibitorKills":0,"perk3Var3":0,"perk3Var2":5,"participantId":6,"perk3Var1":16,"goldSpent":10435,"perk1":8126,"perk0":8124,"perk3":8105,"perk2":8138,"perk5":8347,"perk4":8313,"unrealKills":0,"perk5Var3":0,"perk5Var2":0,"visionScore":32,"perk5Var1":0,"firstBloodKill":false,"longestTimeSpentLiving":974,"killingSprees":2,"sightWardsBoughtInGame":0,"quadraKills":0,"item4":1052,"item3":1402,"item6":3364,"item5":3165,"perkPrimaryStyle":8100,"item0":2055,"item2":3020,"item1":3157,"statPerk1":5008,"statPerk0":5005,"goldEarned":11633,"physicalDamageTaken":15445,"champLevel":15,"totalDamageTaken":26897,"neutralMinionsKilled":165,"statPerk2":5002,"tripleKills":0,"damageSelfMitigated":20893,"largestCriticalStrike":0,"magicDamageDealt":147480,"timeCCingOthers":23,"magicalDamageTaken":10826,"physicalDamageDealtToChampions":959,"perk0Var2":0,"perk0Var1":525,"totalMinionsKilled":28,"visionWardsBoughtInGame":8,"perk0Var3":0,"kills":6,"firstTowerAssist":false,"perk2Var2":0,"perk2Var1":30,"combatPlayerScore":0,"turretKills":0,"trueDamageTaken":626,"firstBloodAssist":false,"assists":7,"damageDealtToTurrets":1058,"win":false,"totalHeal":12725,"perk2Var3":0,"physicalDamageDealt":25673,"trueDamageDealtToChampions":1088,"neutralMinionsKilledEnemyJungle":31,"doubleKills":0,"trueDamageDealt":12229,"perk4Var2":0,"perk4Var1":0,"perk4Var3":0},"teamId":200,"timeline":{"participantId":6,"csDiffPerMinDeltas":{"10-20":-0.19999999999999996,"0-10":-0.3,"20-30":0.6000000000000001},"damageTakenPerMinDeltas":{"10-20":845.5,"0-10":715.5,"20-30":1128.6999999999998},"role":"NONE","damageTakenDiffPerMinDeltas":{"10-20":-350,"0-10":-78.79999999999995,"20-30":254.5999999999999},"xpPerMinDeltas":{"10-20":503.5,"0-10":408.1,"20-30":406.20000000000005},"xpDiffPerMinDeltas":{"10-20":80,"0-10":87.9,"20-30":-127.69999999999999},"lane":"JUNGLE","creepsPerMinDeltas":{"10-20":0.4,"0-10":0.1,"20-30":2.3000000000000003},"goldPerMinDeltas":{"10-20":377.9,"0-10":368.7,"20-30":366.3}},"spell1Id":4,"spell2Id":11},{"participantId":7,"championId":61,"stats":{"totalUnitsHealed":1,"largestMultiKill":2,"firstInhibitorKill":false,"totalPlayerScore":0,"damageDealtToObjectives":5105,"playerScore0":0,"deaths":6,"magicDamageDealtToChampions":11340,"wardsKilled":4,"playerScore7":0,"perkSubStyle":8100,"playerScore8":0,"pentaKills":0,"playerScore5":0,"playerScore6":0,"playerScore3":0,"playerScore4":0,"playerScore1":0,"totalTimeCrowdControlDealt":341,"playerScore2":0,"firstTowerKill":false,"playerScore9":0,"perk1Var3":0,"perk1Var2":1873,"totalScoreRank":0,"perk1Var1":250,"wardsPlaced":11,"totalDamageDealt":157457,"largestKillingSpree":2,"totalDamageDealtToChampions":12391,"neutralMinionsKilledTeamJungle":3,"firstInhibitorAssist":false,"objectivePlayerScore":0,"inhibitorKills":0,"perk3Var3":0,"perk3Var2":0,"participantId":7,"perk3Var1":417,"goldSpent":10550,"perk1":8226,"perk0":8230,"perk3":8237,"perk2":8210,"perk5":8135,"perk4":8139,"unrealKills":0,"perk5Var3":0,"perk5Var2":3,"visionScore":22,"perk5Var1":1980,"firstBloodKill":false,"longestTimeSpentLiving":474,"killingSprees":1,"sightWardsBoughtInGame":0,"quadraKills":0,"item4":3020,"item3":3191,"item6":3363,"item5":1082,"perkPrimaryStyle":8200,"item0":3040,"item2":3907,"item1":1058,"statPerk1":5008,"statPerk0":5005,"goldEarned":11212,"physicalDamageTaken":10974,"champLevel":15,"totalDamageTaken":17186,"neutralMinionsKilled":9,"statPerk2":5002,"tripleKills":0,"damageSelfMitigated":12151,"largestCriticalStrike":0,"magicDamageDealt":141534,"timeCCingOthers":21,"magicalDamageTaken":5999,"physicalDamageDealtToChampions":898,"perk0Var2":0,"perk0Var1":11,"totalMinionsKilled":236,"visionWardsBoughtInGame":2,"perk0Var3":0,"kills":3,"firstTowerAssist":false,"perk2Var2":0,"perk2Var1":0,"combatPlayerScore":0,"turretKills":0,"trueDamageTaken":212,"firstBloodAssist":false,"assists":3,"damageDealtToTurrets":1919,"win":false,"totalHeal":2859,"perk2Var3":0,"physicalDamageDealt":13171,"trueDamageDealtToChampions":153,"neutralMinionsKilledEnemyJungle":0,"doubleKills":1,"trueDamageDealt":2752,"perk4Var2":0,"perk4Var1":811,"perk4Var3":0},"teamId":200,"timeline":{"participantId":7,"csDiffPerMinDeltas":{"10-20":0,"0-10":1.6999999999999995,"20-30":5.5},"damageTakenPerMinDeltas":{"10-20":659.8,"0-10":362.1,"20-30":696.7},"role":"SOLO","damageTakenDiffPerMinDeltas":{"10-20":101.50000000000003,"0-10":-81.79999999999998,"20-30":-313.9},"xpPerMinDeltas":{"10-20":371.8,"0-10":479.6,"20-30":520.2},"xpDiffPerMinDeltas":{"10-20":-139.89999999999998,"0-10":125.60000000000002,"20-30":-1.1000000000000227},"lane":"MIDDLE","creepsPerMinDeltas":{"10-20":6.4,"0-10":7.9,"20-30":9.3},"goldPerMinDeltas":{"10-20":308.70000000000005,"0-10":364.8,"20-30":397.29999999999995}},"spell1Id":12,"spell2Id":4},{"participantId":8,"championId":29,"stats":{"totalUnitsHealed":3,"largestMultiKill":1,"firstInhibitorKill":false,"totalPlayerScore":0,"damageDealtToObjectives":4084,"playerScore0":0,"deaths":5,"magicDamageDealtToChampions":0,"wardsKilled":7,"playerScore7":0,"perkSubStyle":8200,"playerScore8":0,"pentaKills":0,"playerScore5":0,"playerScore6":0,"playerScore3":0,"playerScore4":0,"playerScore1":0,"totalTimeCrowdControlDealt":474,"playerScore2":0,"firstTowerKill":false,"playerScore9":0,"perk1Var3":0,"perk1Var2":500,"totalScoreRank":0,"perk1Var1":1279,"wardsPlaced":11,"totalDamageDealt":118411,"largestKillingSpree":2,"totalDamageDealtToChampions":10435,"neutralMinionsKilledTeamJungle":3,"firstInhibitorAssist":false,"objectivePlayerScore":0,"inhibitorKills":0,"perk3Var3":0,"perk3Var2":0,"participantId":8,"perk3Var1":177,"goldSpent":10600,"perk1":8009,"perk0":8008,"perk3":8014,"perk2":9103,"perk5":8236,"perk4":8275,"unrealKills":0,"perk5Var3":0,"perk5Var2":0,"visionScore":34,"perk5Var1":28,"firstBloodKill":true,"longestTimeSpentLiving":668,"killingSprees":1,"sightWardsBoughtInGame":0,"quadraKills":0,"item4":3042,"item3":3123,"item6":3363,"item5":1038,"perkPrimaryStyle":8000,"item0":3035,"item2":3085,"item1":3006,"statPerk1":5008,"statPerk0":5005,"goldEarned":10514,"physicalDamageTaken":11376,"champLevel":13,"totalDamageTaken":18708,"neutralMinionsKilled":3,"statPerk2":5002,"tripleKills":0,"damageSelfMitigated":9430,"largestCriticalStrike":510,"magicDamageDealt":0,"timeCCingOthers":14,"magicalDamageTaken":7205,"physicalDamageDealtToChampions":8838,"perk0Var2":30,"perk0Var1":2,"totalMinionsKilled":195,"visionWardsBoughtInGame":4,"perk0Var3":0,"kills":3,"firstTowerAssist":false,"perk2Var2":0,"perk2Var1":0,"combatPlayerScore":0,"turretKills":1,"trueDamageTaken":126,"firstBloodAssist":false,"assists":3,"damageDealtToTurrets":1989,"win":false,"totalHeal":1521,"perk2Var3":0,"physicalDamageDealt":107593,"trueDamageDealtToChampions":1596,"neutralMinionsKilledEnemyJungle":0,"doubleKills":0,"trueDamageDealt":10818,"perk4Var2":0,"perk4Var1":8,"perk4Var3":0},"teamId":200,"timeline":{"participantId":8,"damageTakenPerMinDeltas":{"10-20":718.8,"0-10":239.10000000000002,"20-30":912.9000000000001},"role":"DUO","xpPerMinDeltas":{"10-20":459.4,"0-10":292.5,"20-30":383},"lane":"TOP","creepsPerMinDeltas":{"10-20":7.7,"0-10":5.199999999999999,"20-30":6.6},"goldPerMinDeltas":{"10-20":374.9,"0-10":257.7,"20-30":368.4}},"spell1Id":7,"spell2Id":4},{"participantId":9,"championId":43,"stats":{"totalUnitsHealed":5,"largestMultiKill":1,"firstInhibitorKill":false,"totalPlayerScore":0,"damageDealtToObjectives":1533,"playerScore0":0,"deaths":5,"magicDamageDealtToChampions":5748,"wardsKilled":6,"playerScore7":0,"perkSubStyle":8100,"playerScore8":0,"pentaKills":0,"playerScore5":0,"playerScore6":0,"playerScore3":0,"playerScore4":0,"playerScore1":0,"totalTimeCrowdControlDealt":146,"playerScore2":0,"firstTowerKill":false,"playerScore9":0,"perk1Var3":0,"perk1Var2":274,"totalScoreRank":0,"perk1Var1":250,"wardsPlaced":36,"totalDamageDealt":29054,"largestKillingSpree":0,"totalDamageDealtToChampions":6847,"neutralMinionsKilledTeamJungle":0,"firstInhibitorAssist":false,"objectivePlayerScore":0,"inhibitorKills":0,"perk3Var3":0,"perk3Var2":0,"participantId":9,"perk3Var1":394,"goldSpent":6885,"perk1":8226,"perk0":8229,"perk3":8237,"perk2":8210,"perk5":8105,"perk4":8139,"unrealKills":0,"perk5Var3":0,"perk5Var2":5,"visionScore":63,"perk5Var1":16,"firstBloodKill":false,"longestTimeSpentLiving":366,"killingSprees":0,"sightWardsBoughtInGame":0,"quadraKills":0,"item4":2055,"item3":3117,"item6":3364,"item5":1052,"perkPrimaryStyle":8200,"item0":3853,"item2":3174,"item1":3107,"statPerk1":5008,"statPerk0":5008,"goldEarned":7364,"physicalDamageTaken":7282,"champLevel":12,"totalDamageTaken":12050,"neutralMinionsKilled":0,"statPerk2":5002,"tripleKills":0,"damageSelfMitigated":7894,"largestCriticalStrike":0,"magicDamageDealt":20249,"timeCCingOthers":15,"magicalDamageTaken":4768,"physicalDamageDealtToChampions":508,"perk0Var2":0,"perk0Var1":988,"totalMinionsKilled":23,"visionWardsBoughtInGame":10,"perk0Var3":0,"kills":2,"firstTowerAssist":false,"perk2Var2":0,"perk2Var1":0,"combatPlayerScore":0,"turretKills":1,"trueDamageTaken":0,"firstBloodAssist":false,"assists":6,"damageDealtToTurrets":1533,"win":false,"totalHeal":2255,"perk2Var3":0,"physicalDamageDealt":3254,"trueDamageDealtToChampions":590,"neutralMinionsKilledEnemyJungle":0,"doubleKills":0,"trueDamageDealt":5550,"perk4Var2":0,"perk4Var1":731,"perk4Var3":0},"teamId":200,"timeline":{"participantId":9,"damageTakenPerMinDeltas":{"10-20":448.1,"0-10":315.4,"20-30":441.5},"role":"DUO_SUPPORT","xpPerMinDeltas":{"10-20":265.7,"0-10":196.5,"20-30":453.4},"lane":"TOP","creepsPerMinDeltas":{"10-20":0.6000000000000001,"0-10":0.7,"20-30":1},"goldPerMinDeltas":{"10-20":275.6,"0-10":180.3,"20-30":230}},"spell1Id":4,"spell2Id":14},{"participantId":10,"championId":121,"stats":{"totalUnitsHealed":1,"largestMultiKill":1,"firstInhibitorKill":false,"totalPlayerScore":0,"damageDealtToObjectives":8826,"playerScore0":0,"deaths":7,"magicDamageDealtToChampions":865,"wardsKilled":3,"playerScore7":0,"perkSubStyle":8000,"playerScore8":0,"pentaKills":0,"playerScore5":0,"playerScore6":0,"playerScore3":0,"playerScore4":0,"playerScore1":0,"totalTimeCrowdControlDealt":515,"playerScore2":0,"firstTowerKill":false,"playerScore9":0,"perk1Var3":0,"perk1Var2":0,"totalScoreRank":0,"perk1Var1":900,"wardsPlaced":10,"totalDamageDealt":164517,"largestKillingSpree":0,"totalDamageDealtToChampions":15724,"neutralMinionsKilledTeamJungle":0,"firstInhibitorAssist":false,"objectivePlayerScore":0,"inhibitorKills":0,"perk3Var3":0,"perk3Var2":0,"participantId":10,"perk3Var1":28,"goldSpent":11850,"perk1":8224,"perk0":8230,"perk3":8236,"perk2":8233,"perk5":9104,"perk4":8009,"unrealKills":0,"perk5Var3":0,"perk5Var2":20,"visionScore":32,"perk5Var1":16,"firstBloodKill":false,"longestTimeSpentLiving":1036,"killingSprees":0,"sightWardsBoughtInGame":0,"quadraKills":0,"item4":3111,"item3":3147,"item6":3340,"item5":3042,"perkPrimaryStyle":8200,"item0":1036,"item2":3071,"item1":3123,"statPerk1":5008,"statPerk0":5008,"goldEarned":12319,"physicalDamageTaken":13802,"champLevel":15,"totalDamageTaken":26138,"neutralMinionsKilled":8,"statPerk2":5002,"tripleKills":0,"damageSelfMitigated":16841,"largestCriticalStrike":0,"magicDamageDealt":865,"timeCCingOthers":11,"magicalDamageTaken":11594,"physicalDamageDealtToChampions":14829,"perk0Var2":0,"perk0Var1":10,"totalMinionsKilled":222,"visionWardsBoughtInGame":2,"perk0Var3":0,"kills":3,"firstTowerAssist":false,"perk2Var2":40,"perk2Var1":18,"combatPlayerScore":0,"turretKills":3,"trueDamageTaken":740,"firstBloodAssist":false,"assists":5,"damageDealtToTurrets":6339,"win":false,"totalHeal":5866,"perk2Var3":0,"physicalDamageDealt":163622,"trueDamageDealtToChampions":30,"neutralMinionsKilledEnemyJungle":4,"doubleKills":0,"trueDamageDealt":30,"perk4Var2":500,"perk4Var1":1975,"perk4Var3":0},"teamId":200,"timeline":{"participantId":10,"damageTakenPerMinDeltas":{"10-20":726.5,"0-10":536.1,"20-30":1351.2},"role":"DUO","xpPerMinDeltas":{"10-20":617.3,"0-10":437.79999999999995,"20-30":413.1},"lane":"TOP","creepsPerMinDeltas":{"10-20":10,"0-10":5.4,"20-30":6.8},"goldPerMinDeltas":{"10-20":528.3,"0-10":258.2,"20-30":395}},"spell1Id":4,"spell2Id":12}]}