{"gameId":4838627512,"participantIdentities":[{"participantId":1,"player":{"profileIcon":4294,"accountId":"cv2uJ8VPV-y8RS1IUUMBBxsfAKlcgafR3o15QBtSDkQonQ","matchHistoryUri":"\/v1\/stats\/player_history\/EUW1\/42262192","currentAccountId":"cv2uJ8VPV-y8RS1IUUMBBxsfAKlcgafR3o15QBtSDkQonQ","currentPlatformId":"EUW1","summonerName":"Supaaa","summonerId":"6CFV7qHuFwTk-_ihZvd3umWfmsAN2Bhg1zrUWC_iJ6pyIdM","platformId":"EUW1"}},{"participantId":2,"player":{"profileIcon":1297,"accountId":"ndyVieE1D2BA8DfrYDjwX6byoz3_UYt2Q3RpMbKARSG8aA","matchHistoryUri":"\/v1\/stats\/player_history\/EUW1\/22838241","currentAccountId":"ndyVieE1D2BA8DfrYDjwX6byoz3_UYt2Q3RpMbKARSG8aA","currentPlatformId":"EUW1","summonerName":"ebashu v kashu","summonerId":"fmkTYfTe2t0fFwOtmGuNvK09YCL2Hzn-6YD-AVuZV0yKhiw","platformId":"EUW1"}},{"participantId":3,"player":{"profileIcon":4379,"accountId":"NBv-F1yHmceOt2dv9JRqgnMRlqclvQtv5jrXsl2G9K0xbEw","matchHistoryUri":"\/v1\/stats\/player_history\/EUW1\/218247265","currentAccountId":"NBv-F1yHmceOt2dv9JRqgnMRlqclvQtv5jrXsl2G9K0xbEw","currentPlatformId":"EUW1","summonerName":"Quadrakill OY","summonerId":"prR18bGpoZ2Ky5H_vsXjTRhTc7vME89FQpKAZXjlfDP9I6Q","platformId":"EUW1"}},{"participantId":4,"player":{"profileIcon":4661,"accountId":"nBxTyrqPPstP0WxpB9ua4xckkreXKmtWLEL3PyzPaMArdnY","matchHistoryUri":"\/v1\/stats\/player_history\/EUW1\/226506960","currentAccountId":"nBxTyrqPPstP0WxpB9ua4xckkreXKmtWLEL3PyzPaMArdnY","currentPlatformId":"EUW1","summonerName":"Galben","summonerId":"vvHZJx4bn59Ur52xIdJqeAWzb0GtCe4vcZ0vs4-vo-CwSd8","platformId":"EUW1"}},{"participantId":5,"player":{"profileIcon":1225,"accountId":"H6VnSvRw-rlnL_SVMdN15veSzqh0im66tOuSX_HkPVfJc7AYqz23mTEy","matchHistoryUri":"\/v1\/stats\/player_history\/EUW1\/2494451315893280","currentAccountId":"H6VnSvRw-rlnL_SVMdN15veSzqh0im66tOuSX_HkPVfJc7AYqz23mTEy","currentPlatformId":"EUW1","summonerName":"Royalqaq","summonerId":"Z09-MQQWksqmiUqTlI2AX-fqNwxUYY-vdjn0EtwHf7JsDFpB","platformId":"EUW1"}},{"participantId":6,"player":{"profileIcon":4652,"accountId":"ZNmCInHhlBw1OmxxkU92-55HK-pQIcQD1SVwD0tPLAQKu5w","matchHistoryUri":"\/v1\/stats\/player_history\/EUW1\/234264293","currentAccountId":"ZNmCInHhlBw1OmxxkU92-55HK-pQIcQD1SVwD0tPLAQKu5w","currentPlatformId":"EUW1","summonerName":"MYKE TOWERSSS","summonerId":"fxJpFFqpnvfjWRPpZBQ6OmwmVmtFbyuOSl-59JXjjORmpm3-","platformId":"EUW1"}},{"participantId":7,"player":{"profileIcon":4428,"accountId":"_XUZvy9kaRB4HqmI-aSBQWqXkOMbH1AIQcfNNKZ1GbbmeFfuT1CEnI8u","matchHistoryUri":"\/v1\/stats\/player_history\/EUW1\/2030995964211424","currentAccountId":"_XUZvy9kaRB4HqmI-aSBQWqXkOMbH1AIQcfNNKZ1GbbmeFfuT1CEnI8u","currentPlatformId":"EUW1","summonerName":"Diablο v2","summonerId":"gS2d206O5ie0findwemwjNatq_SW_ib6cTum7oTMuyYDeh2o","platformId":"EUW1"}},{"participantId":8,"player":{"profileIcon":1152,"accountId":"DOD5EsxxtsticNzU3jHxVzW_8KEIz9mMxxh1yiyurgF-vXmqeTk99AU9","matchHistoryUri":"\/v1\/stats\/player_history\/TR1\/1984428869022112","currentAccountId":"_BkzYy12msYZElHcQbDVih2NzF4lROa9tKhsFzekqHN_6-zJo6TNujOH","currentPlatformId":"EUW1","summonerName":"θΘθΘθ","summonerId":"lPGMY5q56vGhepvWWJPxOqBo82F1uCY0Vs7IUP1xJMeLiLWl","platformId":"TR1"}},{"participantId":9,"player":{"profileIcon":4711,"accountId":"EICha_y3-tUiBk82NSid6amCD34jD3wv49QcPyDUECT5-Q","matchHistoryUri":"\/v1\/stats\/player_history\/EUW1\/31131524","currentAccountId":"EICha_y3-tUiBk82NSid6amCD34jD3wv49QcPyDUECT5-Q","currentPlatformId":"EUW1","summonerName":"asdf7","summonerId":"sbttO0WjhSt0VPUUgtvKkiTnwSKsmR1V9GkvDAVeTudRGJs","platformId":"EUW1"}},{"participantId":10,"player":{"profileIcon":4568,"accountId":"jFaXOkb9EpWoTX9l0TfD25ayYd0M0R1bNwTirveMgb981fA","matchHistoryUri":"\/v1\/stats\/player_history\/EUW1\/208488800","currentAccountId":"jFaXOkb9EpWoTX9l0TfD25ayYd0M0R1bNwTirveMgb981fA","currentPlatformId":"EUW1","summonerName":"Noltey","summonerId":"n1s90Jw-jsPiJMQ6aoTPfCGwITQGHKLyu2eaGn_MknwLqkU","platformId":"EUW1"}}],"queueId":420,"gameType":"MATCHED_GAME","gameDuration":1448,"teams":[{"towerKills":3,"riftHeraldKills":0,"firstBlood":true,"inhibitorKills":0,"bans":[{"championId":54,"pickTurn":1},{"championId":30,"pickTurn":2},{"championId":11,"pickTurn":3},{"championId":120,"pickTurn":4},{"championId":28,"pickTurn":5}],"firstBaron":false,"firstDragon":true,"dominionVictoryScore":0,"dragonKills":2,"baronKills":0,"firstInhibitor":false,"firstTower":false,"vilemawKills":0,"firstRiftHerald":false,"teamId":100,"win":"Fail"},{"towerKills":5,"riftHeraldKills":2,"firstBlood":false,"inhibitorKills":0,"bans":[{"championId":360,"pickTurn":6},{"championId":55,"pickTurn":7},{"championId":236,"pickTurn":8},{"championId":28,"pickTurn":9},{"championId":92,"pickTurn":10}],"firstBaron":false,"firstDragon":false,"dominionVictoryScore":0,"dragonKills":2,"baronKills":0,"firstInhibitor":false,"firstTower":true,"vilemawKills":0,"firstRiftHerald":true,"teamId":200,"win":"Win"}],"platformId":"EUW1","gameCreation":1601215073054,"seasonId":13,"gameVersion":"10.19.336.4199","mapId":11,"gameMode":"CLASSIC","participants":[{"participantId":1,"championId":22,"stats":{"totalUnitsHealed":3,"largestMultiKill":0,"totalPlayerScore":0,"damageDealtToObjectives":4781,"playerScore0":0,"deaths":7,"magicDamageDealtToChampions":1283,"wardsKilled":6,"playerScore7":0,"perkSubStyle":8300,"playerScore8":0,"pentaKills":0,"playerScore5":0,"playerScore6":0,"playerScore3":0,"playerScore4":0,"playerScore1":0,"totalTimeCrowdControlDealt":771,"playerScore2":0,"firstTowerKill":false,"playerScore9":0,"perk1Var3":0,"perk1Var2":100,"totalScoreRank":0,"perk1Var1":60,"wardsPlaced":5,"totalDamageDealt":115079,"largestKillingSpree":0,"totalDamageDealtToChampions":11544,"neutralMinionsKilledTeamJungle":12,"objectivePlayerScore":0,"inhibitorKills":0,"perk3Var3":0,"perk3Var2":0,"participantId":1,"perk3Var1":443,"goldSpent":8000,"perk1":8009,"perk0":8008,"perk3":8017,"perk2":9104,"perk5":8410,"perk4":8345,"unrealKills":0,"perk5Var3":0,"perk5Var2":0,"visionScore":16,"perk5Var1":88,"firstBloodKill":false,"longestTimeSpentLiving":393,"killingSprees":0,"sightWardsBoughtInGame":0,"quadraKills":0,"item4":1036,"item3":3085,"item6":3363,"item5":1055,"perkPrimaryStyle":8000,"item0":2055,"item2":3006,"item1":3153,"statPerk1":5008,"statPerk0":5005,"goldEarned":8662,"physicalDamageTaken":10101,"champLevel":13,"totalDamageTaken":15886,"neutralMinionsKilled":20,"statPerk2":5002,"tripleKills":0,"damageSelfMitigated":7468,"largestCriticalStrike":239,"magicDamageDealt":2383,"timeCCingOthers":28,"magicalDamageTaken":5546,"physicalDamageDealtToChampions":9754,"perk0Var2":50,"perk0Var1":1,"totalMinionsKilled":200,"visionWardsBoughtInGame":2,"perk0Var3":0,"kills":0,"firstTowerAssist":false,"perk2Var2":40,"perk2Var1":20,"combatPlayerScore":0,"turretKills":1,"trueDamageTaken":238,"firstBloodAssist":false,"assists":1,"damageDealtToTurrets":2735,"win":false,"totalHeal":1976,"perk2Var3":0,"physicalDamageDealt":104870,"trueDamageDealtToChampions":506,"neutralMinionsKilledEnemyJungle":0,"doubleKills":0,"trueDamageDealt":7825,"perk4Var2":0,"perk4Var1":3,"perk4Var3":0},"teamId":100,"timeline":{"participantId":1,"csDiffPerMinDeltas":{"10-20":-0.34999999999999987,"0-10":0.5499999999999998},"damageTakenPerMinDeltas":{"10-20":812.7,"0-10":224.2},"role":"DUO_CARRY","damageTakenDiffPerMinDeltas":{"10-20":94.84999999999997,"0-10":-55.55000000000004},"xpPerMinDeltas":{"10-20":436.29999999999995,"0-10":368.4},"xpDiffPerMinDeltas":{"10-20":-78.20000000000002,"0-10":41.150000000000034},"lane":"BOTTOM","creepsPerMinDeltas":{"10-20":8.1,"0-10":8.3},"goldPerMinDeltas":{"10-20":321.2,"0-10":303}},"spell1Id":7,"spell2Id":4},{"participantId":2,"championId":25,"stats":{"totalUnitsHealed":1,"largestMultiKill":1,"totalPlayerScore":0,"damageDealtToObjectives":828,"playerScore0":0,"deaths":5,"magicDamageDealtToChampions":5371,"wardsKilled":9,"playerScore7":0,"perkSubStyle":8300,"playerScore8":0,"pentaKills":0,"playerScore5":0,"playerScore6":0,"playerScore3":0,"playerScore4":0,"playerScore1":0,"totalTimeCrowdControlDealt":64,"playerScore2":0,"firstTowerKill":false,"playerScore9":0,"perk1Var3":0,"perk1Var2":431,"totalScoreRank":0,"perk1Var1":250,"wardsPlaced":22,"totalDamageDealt":15972,"largestKillingSpree":0,"totalDamageDealtToChampions":6061,"neutralMinionsKilledTeamJungle":0,"objectivePlayerScore":0,"inhibitorKills":0,"perk3Var3":0,"perk3Var2":0,"participantId":2,"perk3Var1":516,"goldSpent":5550,"perk1":8226,"perk0":8229,"perk3":8237,"perk2":8210,"perk5":8345,"perk4":8313,"unrealKills":0,"perk5Var3":0,"perk5Var2":0,"visionScore":53,"perk5Var1":3,"firstBloodKill":false,"longestTimeSpentLiving":418,"killingSprees":0,"sightWardsBoughtInGame":0,"quadraKills":0,"item4":3108,"item3":3158,"item6":3364,"item5":0,"perkPrimaryStyle":8200,"item0":3157,"item2":2055,"item1":3853,"statPerk1":5002,"statPerk0":5008,"goldEarned":5901,"physicalDamageTaken":4807,"champLevel":9,"totalDamageTaken":10406,"neutralMinionsKilled":0,"statPerk2":5002,"tripleKills":0,"damageSelfMitigated":4795,"largestCriticalStrike":0,"magicDamageDealt":12788,"timeCCingOthers":38,"magicalDamageTaken":5570,"physicalDamageDealtToChampions":290,"perk0Var2":0,"perk0Var1":1071,"totalMinionsKilled":17,"visionWardsBoughtInGame":8,"perk0Var3":0,"kills":1,"firstTowerAssist":false,"perk2Var2":0,"perk2Var1":0,"combatPlayerScore":0,"turretKills":0,"trueDamageTaken":28,"firstBloodAssist":false,"assists":4,"damageDealtToTurrets":574,"win":false,"totalHeal":1232,"perk2Var3":0,"physicalDamageDealt":2784,"trueDamageDealtToChampions":400,"neutralMinionsKilledEnemyJungle":0,"doubleKills":0,"trueDamageDealt":400,"perk4Var2":0,"perk4Var1":0,"perk4Var3":0},"teamId":100,"timeline":{"participantId":2,"csDiffPerMinDeltas":{"10-20":-0.34999999999999987,"0-10":0.5499999999999998},"damageTakenPerMinDeltas":{"10-20":535.5,"0-10":194.60000000000002},"role":"DUO_SUPPORT","damageTakenDiffPerMinDeltas":{"10-20":94.84999999999997,"0-10":-55.55000000000004},"xpPerMinDeltas":{"10-20":298.2,"0-10":241.5},"xpDiffPerMinDeltas":{"10-20":-78.20000000000002,"0-10":41.150000000000034},"lane":"BOTTOM","creepsPerMinDeltas":{"10-20":0.6000000000000001,"0-10":0.6},"goldPerMinDeltas":{"10-20":275.70000000000005,"0-10":191}},"spell1Id":4,"spell2Id":14},{"participantId":3,"championId":24,"stats":{"totalUnitsHealed":1,"largestMultiKill":1,"totalPlayerScore":0,"damageDealtToObjectives":5450,"playerScore0":0,"deaths":6,"magicDamageDealtToChampions":3647,"wardsKilled":3,"playerScore7":0,"perkSubStyle":8300,"playerScore8":0,"pentaKills":0,"playerScore5":0,"playerScore6":0,"playerScore3":0,"playerScore4":0,"playerScore1":0,"totalTimeCrowdControlDealt":58,"playerScore2":0,"firstTowerKill":false,"playerScore9":0,"perk1Var3":0,"perk1Var2":60,"totalScoreRank":0,"perk1Var1":328,"wardsPlaced":9,"totalDamageDealt":100309,"largestKillingSpree":0,"totalDamageDealtToChampions":10065,"neutralMinionsKilledTeamJungle":1,"objectivePlayerScore":0,"inhibitorKills":0,"perk3Var3":0,"perk3Var2":0,"participantId":3,"perk3Var1":565,"goldSpent":8933,"perk1":9111,"perk0":8010,"perk3":8299,"perk2":9104,"perk5":8352,"perk4":8345,"unrealKills":0,"perk5Var3":1088,"perk5Var2":1909,"visionScore":17,"perk5Var1":317,"firstBloodKill":false,"longestTimeSpentLiving":338,"killingSprees":0,"sightWardsBoughtInGame":0,"quadraKills":0,"item4":3133,"item3":3111,"item6":3340,"item5":3105,"perkPrimaryStyle":8000,"item0":2033,"item2":3078,"item1":3077,"statPerk1":5008,"statPerk0":5005,"goldEarned":9393,"physicalDamageTaken":9978,"champLevel":13,"totalDamageTaken":17413,"neutralMinionsKilled":8,"statPerk2":5002,"tripleKills":0,"damageSelfMitigated":12755,"largestCriticalStrike":0,"magicDamageDealt":18836,"timeCCingOthers":14,"magicalDamageTaken":7013,"physicalDamageDealtToChampions":6418,"perk0Var2":0,"perk0Var1":384,"totalMinionsKilled":160,"visionWardsBoughtInGame":1,"perk0Var3":0,"kills":1,"firstTowerAssist":false,"perk2Var2":0,"perk2Var1":0,"combatPlayerScore":0,"turretKills":2,"trueDamageTaken":422,"firstBloodAssist":false,"assists":2,"damageDealtToTurrets":4635,"win":false,"totalHeal":3247,"perk2Var3":0,"physicalDamageDealt":81473,"trueDamageDealtToChampions":0,"neutralMinionsKilledEnemyJungle":4,"doubleKills":0,"trueDamageDealt":0,"perk4Var2":0,"perk4Var1":3,"perk4Var3":0},"teamId":100,"timeline":{"participantId":3,"csDiffPerMinDeltas":{"10-20":5.199999999999999,"0-10":-0.7999999999999998},"damageTakenPerMinDeltas":{"10-20":812.9000000000001,"0-10":527.5},"role":"SOLO","damageTakenDiffPerMinDeltas":{"10-20":-200.39999999999992,"0-10":191.8},"xpPerMinDeltas":{"10-20":561.2,"0-10":395.5},"xpDiffPerMinDeltas":{"10-20":141.7,"0-10":-113.29999999999998},"lane":"TOP","creepsPerMinDeltas":{"10-20":9.399999999999999,"0-10":5.5},"goldPerMinDeltas":{"10-20":574.9,"0-10":221.8}},"spell1Id":4,"spell2Id":12},{"participantId":4,"championId":2,"stats":{"totalUnitsHealed":1,"largestMultiKill":2,"totalPlayerScore":0,"damageDealtToObjectives":21285,"playerScore0":0,"deaths":6,"magicDamageDealtToChampions":0,"wardsKilled":7,"playerScore7":0,"perkSubStyle":8300,"playerScore8":0,"pentaKills":0,"playerScore5":0,"playerScore6":0,"playerScore3":0,"playerScore4":0,"playerScore1":0,"totalTimeCrowdControlDealt":337,"playerScore2":0,"firstTowerKill":false,"playerScore9":0,"perk1Var3":0,"perk1Var2":100,"totalScoreRank":0,"perk1Var1":359,"wardsPlaced":2,"totalDamageDealt":120211,"largestKillingSpree":2,"totalDamageDealtToChampions":8817,"neutralMinionsKilledTeamJungle":59,"objectivePlayerScore":0,"inhibitorKills":0,"perk3Var3":0,"perk3Var2":0,"participantId":4,"perk3Var1":327,"goldSpent":7175,"perk1":9111,"perk0":8010,"perk3":8299,"perk2":9104,"perk5":8410,"perk4":8304,"unrealKills":0,"perk5Var3":0,"perk5Var2":0,"visionScore":17,"perk5Var1":38,"firstBloodKill":true,"longestTimeSpentLiving":843,"killingSprees":1,"sightWardsBoughtInGame":0,"quadraKills":0,"item4":0,"item3":3071,"item6":3364,"item5":3047,"perkPrimaryStyle":8000,"item0":1400,"item2":1033,"item1":2031,"statPerk1":5008,"statPerk0":5008,"goldEarned":7868,"physicalDamageTaken":13578,"champLevel":11,"totalDamageTaken":22856,"neutralMinionsKilled":101,"statPerk2":5002,"tripleKills":0,"damageSelfMitigated":14586,"largestCriticalStrike":0,"magicDamageDealt":4783,"timeCCingOthers":8,"magicalDamageTaken":9192,"physicalDamageDealtToChampions":6654,"perk0Var2":0,"perk0Var1":305,"totalMinionsKilled":21,"visionWardsBoughtInGame":2,"perk0Var3":0,"kills":4,"firstTowerAssist":false,"perk2Var2":50,"perk2Var1":13,"combatPlayerScore":0,"turretKills":0,"trueDamageTaken":86,"firstBloodAssist":false,"assists":1,"damageDealtToTurrets":0,"win":false,"totalHeal":7643,"perk2Var3":0,"physicalDamageDealt":100049,"trueDamageDealtToChampions":2162,"neutralMinionsKilledEnemyJungle":17,"doubleKills":1,"trueDamageDealt":15378,"perk4Var2":1,"perk4Var1":11,"perk4Var3":5},"teamId":100,"timeline":{"participantId":4,"damageTakenPerMinDeltas":{"10-20":1091.7,"0-10":712.4},"role":"NONE","xpPerMinDeltas":{"10-20":343.3,"0-10":339.4},"lane":"JUNGLE","creepsPerMinDeltas":{"10-20":0.5,"0-10":0.2},"goldPerMinDeltas":{"10-20":347,"0-10":291.6}},"spell1Id":11,"spell2Id":4},{"participantId":5,"championId":157,"stats":{"totalUnitsHealed":1,"largestMultiKill":1,"totalPlayerScore":0,"damageDealtToObjectives":1653,"playerScore0":0,"deaths":4,"magicDamageDealtToChampions":769,"wardsKilled":0,"playerScore7":0,"perkSubStyle":8100,"playerScore8":0,"pentaKills":0,"playerScore5":0,"playerScore6":0,"playerScore3":0,"playerScore4":0,"playerScore1":0,"totalTimeCrowdControlDealt":99,"playerScore2":0,"firstTowerKill":false,"playerScore9":0,"perk1Var3":0,"perk1Var2":40,"totalScoreRank":0,"perk1Var1":0,"wardsPlaced":7,"totalDamageDealt":125469,"largestKillingSpree":0,"totalDamageDealtToChampions":8804,"neutralMinionsKilledTeamJungle":8,"objectivePlayerScore":0,"inhibitorKills":0,"perk3Var3":0,"perk3Var2":0,"participantId":5,"perk3Var1":48,"goldSpent":8250,"perk1":9111,"perk0":8021,"perk3":8014,"perk2":9104,"perk5":8135,"perk4":8139,"unrealKills":0,"perk5Var3":0,"perk5Var2":2,"visionScore":16,"perk5Var1":656,"firstBloodKill":false,"longestTimeSpentLiving":910,"killingSprees":0,"sightWardsBoughtInGame":0,"quadraKills":0,"item4":0,"item3":3046,"item6":3363,"item5":0,"perkPrimaryStyle":8000,"item0":1055,"item2":3006,"item1":3031,"statPerk1":5008,"statPerk0":5005,"goldEarned":8319,"physicalDamageTaken":8436,"champLevel":13,"totalDamageTaken":15161,"neutralMinionsKilled":8,"statPerk2":5003,"tripleKills":0,"damageSelfMitigated":15622,"largestCriticalStrike":472,"magicDamageDealt":11805,"timeCCingOthers":15,"magicalDamageTaken":6435,"physicalDamageDealtToChampions":7229,"perk0Var2":0,"perk0Var1":1453,"totalMinionsKilled":190,"visionWardsBoughtInGame":2,"perk0Var3":0,"kills":1,"firstTowerAssist":false,"perk2Var2":20,"perk2Var1":20,"combatPlayerScore":0,"turretKills":0,"trueDamageTaken":290,"firstBloodAssist":false,"assists":1,"damageDealtToTurrets":993,"win":false,"totalHeal":3105,"perk2Var3":0,"physicalDamageDealt":112857,"trueDamageDealtToChampions":806,"neutralMinionsKilledEnemyJungle":0,"doubleKills":0,"trueDamageDealt":806,"perk4Var2":0,"perk4Var1":601,"perk4Var3":0},"teamId":100,"timeline":{"participantId":5,"damageTakenPerMinDeltas":{"10-20":907.1,"0-10":252.2},"role":"SOLO","xpPerMinDeltas":{"10-20":480.7,"0-10":443.3},"lane":"MIDDLE","creepsPerMinDeltas":{"10-20":8.5,"0-10":7.4},"goldPerMinDeltas":{"10-20":379.9,"0-10":280.1}},"spell1Id":4,"spell2Id":14},{"participantId":6,"championId":202,"stats":{"totalUnitsHealed":1,"largestMultiKill":1,"totalPlayerScore":0,"damageDealtToObjectives":4404,"playerScore0":0,"deaths":2,"magicDamageDealtToChampions":1086,"wardsKilled":1,"playerScore7":0,"perkSubStyle":8200,"playerScore8":0,"pentaKills":0,"playerScore5":0,"playerScore6":0,"playerScore3":0,"playerScore4":0,"playerScore1":0,"totalTimeCrowdControlDealt":110,"playerScore2":0,"firstTowerKill":false,"playerScore9":0,"perk1Var3":0,"perk1Var2":500,"totalScoreRank":0,"perk1Var1":2191,"wardsPlaced":6,"totalDamageDealt":131040,"largestKillingSpree":4,"totalDamageDealtToChampions":12678,"neutralMinionsKilledTeamJungle":8,"objectivePlayerScore":0,"inhibitorKills":0,"perk3Var3":0,"perk3Var2":0,"participantId":6,"perk3Var1":195,"goldSpent":9925,"perk1":8009,"perk0":8021,"perk3":8017,"perk2":9103,"perk5":8236,"perk4":8275,"unrealKills":0,"perk5Var3":0,"perk5Var2":0,"visionScore":11,"perk5Var1":14,"firstBloodKill":false,"longestTimeSpentLiving":644,"killingSprees":2,"sightWardsBoughtInGame":0,"quadraKills":0,"item4":1038,"item3":3031,"item6":3363,"item5":3047,"perkPrimaryStyle":8000,"item0":1055,"item2":1018,"item1":3094,"statPerk1":5008,"statPerk0":5008,"goldEarned":10720,"physicalDamageTaken":8779,"champLevel":13,"totalDamageTaken":11207,"neutralMinionsKilled":14,"statPerk2":5002,"tripleKills":0,"damageSelfMitigated":6929,"largestCriticalStrike":928,"magicDamageDealt":6924,"timeCCingOthers":10,"magicalDamageTaken":1952,"physicalDamageDealtToChampions":11472,"perk0Var2":0,"perk0Var1":1655,"totalMinionsKilled":178,"visionWardsBoughtInGame":1,"perk0Var3":0,"kills":6,"firstTowerAssist":true,"perk2Var2":0,"perk2Var1":23,"combatPlayerScore":0,"turretKills":1,"trueDamageTaken":476,"firstBloodAssist":false,"assists":7,"damageDealtToTurrets":2836,"win":true,"totalHeal":1764,"perk2Var3":0,"physicalDamageDealt":123644,"trueDamageDealtToChampions":120,"neutralMinionsKilledEnemyJungle":2,"doubleKills":0,"trueDamageDealt":472,"perk4Var2":0,"perk4Var1":9,"perk4Var3":0},"teamId":200,"timeline":{"participantId":6,"csDiffPerMinDeltas":{"10-20":0.34999999999999987,"0-10":-0.5499999999999998},"damageTakenPerMinDeltas":{"10-20":583.6,"0-10":314.20000000000005},"role":"DUO_CARRY","damageTakenDiffPerMinDeltas":{"10-20":-94.84999999999997,"0-10":55.55000000000004},"xpPerMinDeltas":{"10-20":525.7,"0-10":299.9},"xpDiffPerMinDeltas":{"10-20":78.20000000000002,"0-10":-41.150000000000034},"lane":"BOTTOM","creepsPerMinDeltas":{"10-20":7.8999999999999995,"0-10":6.1},"goldPerMinDeltas":{"10-20":572.3,"0-10":270.8}},"spell1Id":4,"spell2Id":1},{"participantId":7,"championId":136,"stats":{"totalUnitsHealed":1,"largestMultiKill":1,"totalPlayerScore":0,"damageDealtToObjectives":1846,"playerScore0":0,"deaths":0,"magicDamageDealtToChampions":15423,"wardsKilled":1,"playerScore7":0,"perkSubStyle":8400,"playerScore8":0,"pentaKills":0,"playerScore5":0,"playerScore6":0,"playerScore3":0,"playerScore4":0,"playerScore1":0,"totalTimeCrowdControlDealt":86,"playerScore2":0,"firstTowerKill":false,"playerScore9":0,"perk1Var3":0,"perk1Var2":1488,"totalScoreRank":0,"perk1Var1":250,"wardsPlaced":9,"totalDamageDealt":134312,"largestKillingSpree":10,"totalDamageDealtToChampions":18972,"neutralMinionsKilledTeamJungle":10,"objectivePlayerScore":0,"inhibitorKills":0,"perk3Var3":0,"perk3Var2":0,"participantId":7,"perk3Var1":504,"goldSpent":11050,"perk1":8226,"perk0":8230,"perk3":8237,"perk2":8234,"perk5":8451,"perk4":8473,"unrealKills":0,"perk5Var3":0,"perk5Var2":0,"visionScore":18,"perk5Var1":179,"firstBloodKill":false,"longestTimeSpentLiving":0,"killingSprees":1,"sightWardsBoughtInGame":0,"quadraKills":0,"item4":3916,"item3":3047,"item6":3363,"item5":3151,"perkPrimaryStyle":8200,"item0":3030,"item2":3041,"item1":2033,"statPerk1":5002,"statPerk0":5005,"goldEarned":11807,"physicalDamageTaken":8842,"champLevel":15,"totalDamageTaken":10773,"neutralMinionsKilled":17,"statPerk2":5002,"tripleKills":0,"damageSelfMitigated":8440,"largestCriticalStrike":0,"magicDamageDealt":121249,"timeCCingOthers":15,"magicalDamageTaken":855,"physicalDamageDealtToChampions":2781,"perk0Var2":0,"perk0Var1":24,"totalMinionsKilled":188,"visionWardsBoughtInGame":2,"perk0Var3":0,"kills":10,"firstTowerAssist":false,"perk2Var2":0,"perk2Var1":10091,"combatPlayerScore":0,"turretKills":1,"trueDamageTaken":1075,"firstBloodAssist":false,"assists":8,"damageDealtToTurrets":1846,"win":true,"totalHeal":284,"perk2Var3":0,"physicalDamageDealt":12294,"trueDamageDealtToChampions":768,"neutralMinionsKilledEnemyJungle":7,"doubleKills":0,"trueDamageDealt":768,"perk4Var2":0,"perk4Var1":481,"perk4Var3":0},"teamId":200,"timeline":{"participantId":7,"damageTakenPerMinDeltas":{"10-20":564,"0-10":185.39999999999998},"role":"NONE","xpPerMinDeltas":{"10-20":590.5,"0-10":515},"lane":"JUNGLE","creepsPerMinDeltas":{"10-20":8.100000000000001,"0-10":8.8},"goldPerMinDeltas":{"10-20":498.4,"0-10":350.4}},"spell1Id":14,"spell2Id":4},{"participantId":8,"championId":412,"stats":{"totalUnitsHealed":3,"largestMultiKill":0,"totalPlayerScore":0,"damageDealtToObjectives":3425,"playerScore0":0,"deaths":2,"magicDamageDealtToChampions":2293,"wardsKilled":7,"playerScore7":0,"perkSubStyle":8300,"playerScore8":0,"pentaKills":0,"playerScore5":0,"playerScore6":0,"playerScore3":0,"playerScore4":0,"playerScore1":0,"totalTimeCrowdControlDealt":56,"playerScore2":0,"firstTowerKill":false,"playerScore9":0,"perk1Var3":0,"perk1Var2":0,"totalScoreRank":0,"perk1Var1":556,"wardsPlaced":26,"totalDamageDealt":17231,"largestKillingSpree":0,"totalDamageDealtToChampions":3069,"neutralMinionsKilledTeamJungle":0,"objectivePlayerScore":0,"inhibitorKills":0,"perk3Var3":0,"perk3Var2":0,"participantId":8,"perk3Var1":31,"goldSpent":6275,"perk1":8446,"perk0":8465,"perk3":8242,"perk2":8444,"perk5":8316,"perk4":8313,"unrealKills":0,"perk5Var3":0,"perk5Var2":0,"visionScore":59,"perk5Var1":395,"firstBloodKill":false,"longestTimeSpentLiving":822,"killingSprees":0,"sightWardsBoughtInGame":0,"quadraKills":0,"item4":0,"item3":0,"item6":3364,"item5":3009,"perkPrimaryStyle":8400,"item0":3222,"item2":3860,"item1":3107,"statPerk1":5003,"statPerk0":5007,"goldEarned":6598,"physicalDamageTaken":6377,"champLevel":11,"totalDamageTaken":8390,"neutralMinionsKilled":0,"statPerk2":5002,"tripleKills":0,"damageSelfMitigated":7145,"largestCriticalStrike":0,"magicDamageDealt":6238,"timeCCingOthers":20,"magicalDamageTaken":1465,"physicalDamageDealtToChampions":776,"perk0Var2":0,"perk0Var1":1103,"totalMinionsKilled":34,"visionWardsBoughtInGame":9,"perk0Var3":0,"kills":0,"firstTowerAssist":true,"perk2Var2":0,"perk2Var1":572,"combatPlayerScore":0,"turretKills":0,"trueDamageTaken":546,"firstBloodAssist":false,"assists":16,"damageDealtToTurrets":1012,"win":true,"totalHeal":956,"perk2Var3":0,"physicalDamageDealt":4989,"trueDamageDealtToChampions":0,"neutralMinionsKilledEnemyJungle":0,"doubleKills":0,"trueDamageDealt":6003,"perk4Var2":0,"perk4Var1":0,"perk4Var3":0},"teamId":200,"timeline":{"participantId":8,"csDiffPerMinDeltas":{"10-20":0.34999999999999987,"0-10":-0.5499999999999998},"damageTakenPerMinDeltas":{"10-20":574.9,"0-10":215.7},"role":"DUO_SUPPORT","damageTakenDiffPerMinDeltas":{"10-20":-94.84999999999997,"0-10":55.55000000000004},"xpPerMinDeltas":{"10-20":365.20000000000005,"0-10":227.7},"xpDiffPerMinDeltas":{"10-20":78.20000000000002,"0-10":-41.150000000000034},"lane":"BOTTOM","creepsPerMinDeltas":{"10-20":1.5,"0-10":1.7},"goldPerMinDeltas":{"10-20":331.7,"0-10":172.8}},"spell1Id":3,"spell2Id":4},{"participantId":9,"championId":78,"stats":{"totalUnitsHealed":1,"largestMultiKill":2,"totalPlayerScore":0,"damageDealtToObjectives":3450,"playerScore0":0,"deaths":2,"magicDamageDealtToChampions":4254,"wardsKilled":1,"playerScore7":0,"perkSubStyle":8300,"playerScore8":0,"pentaKills":0,"playerScore5":0,"playerScore6":0,"playerScore3":0,"playerScore4":0,"playerScore1":0,"totalTimeCrowdControlDealt":431,"playerScore2":0,"firstTowerKill":false,"playerScore9":0,"perk1Var3":0,"perk1Var2":0,"totalScoreRank":0,"perk1Var1":133,"wardsPlaced":12,"totalDamageDealt":76690,"largestKillingSpree":3,"totalDamageDealtToChampions":14427,"neutralMinionsKilledTeamJungle":0,"objectivePlayerScore":0,"inhibitorKills":0,"perk3Var3":0,"perk3Var2":0,"participantId":9,"perk3Var1":161,"goldSpent":7300,"perk1":8401,"perk0":8437,"perk3":8451,"perk2":8473,"perk5":8345,"perk4":8352,"unrealKills":0,"perk5Var3":0,"perk5Var2":0,"visionScore":22,"perk5Var1":3,"firstBloodKill":false,"longestTimeSpentLiving":981,"killingSprees":2,"sightWardsBoughtInGame":0,"quadraKills":0,"item4":3211,"item3":3068,"item6":3363,"item5":1033,"perkPrimaryStyle":8400,"item0":2033,"item2":3047,"item1":3076,"statPerk1":5008,"statPerk0":5008,"goldEarned":8183,"physicalDamageTaken":9608,"champLevel":13,"totalDamageTaken":15768,"neutralMinionsKilled":2,"statPerk2":5002,"tripleKills":0,"damageSelfMitigated":21337,"largestCriticalStrike":14,"magicDamageDealt":20548,"timeCCingOthers":39,"magicalDamageTaken":4756,"physicalDamageDealtToChampions":10173,"perk0Var2":487,"perk0Var1":679,"totalMinionsKilled":125,"visionWardsBoughtInGame":4,"perk0Var3":0,"kills":6,"firstTowerAssist":false,"perk2Var2":0,"perk2Var1":636,"combatPlayerScore":0,"turretKills":0,"trueDamageTaken":1403,"firstBloodAssist":false,"assists":5,"damageDealtToTurrets":0,"win":true,"totalHeal":2488,"perk2Var3":0,"physicalDamageDealt":55917,"trueDamageDealtToChampions":0,"neutralMinionsKilledEnemyJungle":1,"doubleKills":1,"trueDamageDealt":224,"perk4Var2":1724,"perk4Var1":381,"perk4Var3":1161},"teamId":200,"timeline":{"participantId":9,"csDiffPerMinDeltas":{"10-20":-5.199999999999999,"0-10":0.7999999999999998},"damageTakenPerMinDeltas":{"10-20":1013.3,"0-10":335.7},"role":"SOLO","damageTakenDiffPerMinDeltas":{"10-20":200.39999999999992,"0-10":-191.8},"xpPerMinDeltas":{"10-20":419.5,"0-10":508.79999999999995},"xpDiffPerMinDeltas":{"10-20":-141.7,"0-10":113.29999999999998},"lane":"TOP","creepsPerMinDeltas":{"10-20":4.199999999999999,"0-10":6.3},"goldPerMinDeltas":{"10-20":358.1,"0-10":282.4}},"spell1Id":4,"spell2Id":12},{"participantId":10,"championId":76,"stats":{"totalUnitsHealed":4,"largestMultiKill":3,"totalPlayerScore":0,"damageDealtToObjectives":28997,"playerScore0":0,"deaths":1,"magicDamageDealtToChampions":9355,"wardsKilled":9,"playerScore7":0,"perkSubStyle":8100,"playerScore8":0,"pentaKills":0,"playerScore5":0,"playerScore6":0,"playerScore3":0,"playerScore4":0,"playerScore1":0,"totalTimeCrowdControlDealt":124,"playerScore2":0,"firstTowerKill":true,"playerScore9":0,"perk1Var3":0,"perk1Var2":500,"totalScoreRank":0,"perk1Var1":2156,"wardsPlaced":21,"totalDamageDealt":159880,"largestKillingSpree":6,"totalDamageDealtToChampions":10553,"neutralMinionsKilledTeamJungle":90,"objectivePlayerScore":0,"inhibitorKills":0,"perk3Var3":0,"perk3Var2":0,"participantId":10,"perk3Var1":355,"goldSpent":10450,"perk1":8009,"perk0":8010,"perk3":8014,"perk2":9105,"perk5":8136,"perk4":8135,"unrealKills":0,"perk5Var3":0,"perk5Var2":30,"visionScore":48,"perk5Var1":13,"firstBloodKill":false,"longestTimeSpentLiving":271,"killingSprees":1,"sightWardsBoughtInGame":0,"quadraKills":0,"item4":3174,"item3":3041,"item6":3364,"item5":2055,"perkPrimaryStyle":8000,"item0":3047,"item2":3027,"item1":1414,"statPerk1":5008,"statPerk0":5005,"goldEarned":10792,"physicalDamageTaken":15015,"champLevel":14,"totalDamageTaken":20463,"neutralMinionsKilled":152,"statPerk2":5002,"tripleKills":1,"damageSelfMitigated":11836,"largestCriticalStrike":0,"magicDamageDealt":120033,"timeCCingOthers":0,"magicalDamageTaken":5076,"physicalDamageDealtToChampions":1021,"perk0Var2":0,"perk0Var1":47,"totalMinionsKilled":26,"visionWardsBoughtInGame":8,"perk0Var3":0,"kills":6,"firstTowerAssist":false,"perk2Var2":50,"perk2Var1":13,"combatPlayerScore":0,"turretKills":3,"trueDamageTaken":372,"firstBloodAssist":false,"assists":7,"damageDealtToTurrets":2504,"win":true,"totalHeal":16113,"perk2Var3":0,"physicalDamageDealt":25011,"trueDamageDealtToChampions":176,"neutralMinionsKilledEnemyJungle":23,"doubleKills":1,"trueDamageDealt":14834,"perk4Var2":5,"perk4Var1":2815,"perk4Var3":0},"teamId":200,"timeline":{"participantId":10,"damageTakenPerMinDeltas":{"10-20":841.6,"0-10":770.7},"role":"NONE","xpPerMinDeltas":{"10-20":629.8,"0-10":359.6},"lane":"JUNGLE","creepsPerMinDeltas":{"10-20":2.1,"0-10":0.3},"goldPerMinDeltas":{"10-20":538.1,"0-10":270.7}},"spell1Id":4,"spell2Id":11}]}