{"frames":[{"participantFrames":{"1":{"participantId":4,"minionsKilled":0,"teamScore":0,"dominionScore":0,"totalGold":500,"level":1,"xp":0,"currentGold":500,"position":{"x":560,"y":581},"jungleMinionsKilled":0},"2":{"participantId":5,"minionsKilled":0,"teamScore":0,"dominionScore":0,"totalGold":500,"level":1,"xp":0,"currentGold":500,"position":{"x":560,"y":361},"jungleMinionsKilled":0},"3":{"participantId":3,"minionsKilled":0,"teamScore":0,"dominionScore":0,"totalGold":500,"level":1,"xp":0,"currentGold":500,"position":{"x":351,"y":293},"jungleMinionsKilled":0},"4":{"participantId":2,"minionsKilled":0,"teamScore":0,"dominionScore":0,"totalGold":500,"level":1,"xp":0,"currentGold":500,"position":{"x":221,"y":471},"jungleMinionsKilled":0},"5":{"participantId":1,"minionsKilled":0,"teamScore":0,"dominionScore":0,"totalGold":500,"level":1,"xp":0,"currentGold":500,"position":{"x":311,"y":649},"jungleMinionsKilled":0},"6":{"participantId":7,"minionsKilled":0,"teamScore":0,"dominionScore":0,"totalGold":500,"level":1,"xp":0,"currentGold":500,"position":{"x":14486,"y":14511},"jungleMinionsKilled":0},"7":{"participantId":6,"minionsKilled":0,"teamScore":0,"dominionScore":0,"totalGold":500,"level":1,"xp":0,"currentGold":500,"position":{"x":14486,"y":14291},"jungleMinionsKilled":0},"8":{"participantId":10,"minionsKilled":0,"teamScore":0,"dominionScore":0,"totalGold":500,"level":1,"xp":0,"currentGold":500,"position":{"x":14277,"y":14223},"jungleMinionsKilled":0},"9":{"participantId":8,"minionsKilled":0,"teamScore":0,"dominionScore":0,"totalGold":500,"level":1,"xp":0,"currentGold":500,"position":{"x":14147,"y":14401},"jungleMinionsKilled":0},"10":{"participantId":9,"minionsKilled":0,"teamScore":0,"dominionScore":0,"totalGold":500,"level":1,"xp":0,"currentGold":500,"position":{"x":14237,"y":14579},"jungleMinionsKilled":0}},"events":[],"timestamp":0},{"participantFrames":{"1":{"participantId":4,"minionsKilled":0,"teamScore":0,"dominionScore":0,"totalGold":500,"level":1,"xp":0,"currentGold":0,"position":{"x":3555,"y":9486},"jungleMinionsKilled":0},"2":{"participantId":5,"minionsKilled":0,"teamScore":0,"dominionScore":0,"totalGold":500,"level":1,"xp":0,"currentGold":0,"position":{"x":6950,"y":4758},"jungleMinionsKilled":0},"3":{"participantId":3,"minionsKilled":0,"teamScore":0,"dominionScore":0,"totalGold":500,"level":1,"xp":0,"currentGold":0,"position":{"x":6235,"y":8133},"jungleMinionsKilled":0},"4":{"participantId":2,"minionsKilled":0,"teamScore":0,"dominionScore":0,"totalGold":500,"level":1,"xp":0,"currentGold":0,"position":{"x":10353,"y":2974},"jungleMinionsKilled":0},"5":{"participantId":1,"minionsKilled":0,"teamScore":0,"dominionScore":0,"totalGold":500,"level":1,"xp":0,"currentGold":0,"position":{"x":8120,"y":3525},"jungleMinionsKilled":0},"6":{"participantId":7,"minionsKilled":0,"teamScore":0,"dominionScore":0,"totalGold":500,"level":1,"xp":0,"currentGold":0,"position":{"x":4478,"y":11500},"jungleMinionsKilled":0},"7":{"participantId":6,"minionsKilled":0,"teamScore":0,"dominionScore":0,"totalGold":500,"level":1,"xp":0,"currentGold":0,"position":{"x":8924,"y":7880},"jungleMinionsKilled":0},"8":{"participantId":10,"minionsKilled":0,"teamScore":0,"dominionScore":0,"totalGold":500,"level":1,"xp":0,"currentGold":0,"position":{"x":8380,"y":6436},"jungleMinionsKilled":0},"9":{"participantId":8,"minionsKilled":0,"teamScore":0,"dominionScore":0,"totalGold":500,"level":1,"xp":0,"currentGold":0,"position":{"x":11750,"y":3817},"jungleMinionsKilled":0},"10":{"participantId":9,"minionsKilled":0,"teamScore":0,"dominionScore":0,"totalGold":500,"level":1,"xp":0,"currentGold":0,"position":{"x":11690,"y":2846},"jungleMinionsKilled":0}},"events":[{"participantId":3,"itemId":2033,"type":"ITEM_PURCHASED","timestamp":3313},{"participantId":1,"itemId":3850,"type":"ITEM_PURCHASED","timestamp":3445},{"participantId":4,"itemId":2003,"type":"ITEM_PURCHASED","timestamp":3478},{"participantId":9,"itemId":2003,"type":"ITEM_PURCHASED","timestamp":3511},{"participantId":9,"itemId":3850,"type":"ITEM_PURCHASED","timestamp":3676},{"participantId":4,"itemId":3340,"type":"ITEM_PURCHASED","timestamp":3775},{"participantId":1,"itemId":2003,"type":"ITEM_PURCHASED","timestamp":3808},{"participantId":9,"itemId":2003,"type":"ITEM_PURCHASED","timestamp":3841},{"participantId":3,"itemId":3340,"type":"ITEM_PURCHASED","timestamp":3841},{"participantId":1,"itemId":2003,"type":"ITEM_PURCHASED","timestamp":3940},{"participantId":9,"itemId":3340,"type":"ITEM_PURCHASED","timestamp":4008},{"participantId":1,"itemId":3340,"type":"ITEM_PURCHASED","timestamp":4272},{"participantId":4,"itemId":1055,"type":"ITEM_PURCHASED","timestamp":4371},{"participantId":6,"itemId":1041,"type":"ITEM_PURCHASED","timestamp":4833},{"participantId":2,"itemId":1055,"type":"ITEM_PURCHASED","timestamp":4998},{"participantId":6,"itemId":2031,"type":"ITEM_PURCHASED","timestamp":5163},{"participantId":2,"itemId":2003,"type":"ITEM_PURCHASED","timestamp":5229},{"participantId":6,"itemId":3340,"type":"ITEM_PURCHASED","timestamp":5428},{"participantId":2,"itemId":3340,"type":"ITEM_PURCHASED","timestamp":5758},{"participantId":8,"itemId":1056,"type":"ITEM_PURCHASED","timestamp":6121},{"participantId":8,"itemId":2003,"type":"ITEM_PURCHASED","timestamp":6319},{"participantId":8,"itemId":2003,"type":"ITEM_PURCHASED","timestamp":6451},{"participantId":8,"itemId":3340,"type":"ITEM_PURCHASED","timestamp":6683},{"participantId":2,"skillSlot":3,"type":"SKILL_LEVEL_UP","timestamp":8236,"levelUpType":"NORMAL"},{"participantId":10,"itemId":2033,"type":"ITEM_PURCHASED","timestamp":14448},{"participantId":7,"itemId":3340,"type":"ITEM_PURCHASED","timestamp":15208},{"participantId":7,"itemId":1054,"type":"ITEM_PURCHASED","timestamp":15439},{"participantId":7,"itemId":2003,"type":"ITEM_PURCHASED","timestamp":15604},{"participantId":5,"itemId":1039,"type":"ITEM_PURCHASED","timestamp":19138},{"participantId":5,"itemId":1006,"type":"ITEM_PURCHASED","timestamp":19930},{"participantId":5,"itemId":3340,"type":"ITEM_PURCHASED","timestamp":20327},{"participantId":5,"skillSlot":2,"type":"SKILL_LEVEL_UP","timestamp":26304,"levelUpType":"NORMAL"},{"participantId":10,"skillSlot":1,"type":"SKILL_LEVEL_UP","timestamp":26469,"levelUpType":"NORMAL"},{"participantId":8,"skillSlot":1,"type":"SKILL_LEVEL_UP","timestamp":26965,"levelUpType":"NORMAL"},{"participantId":1,"skillSlot":1,"type":"SKILL_LEVEL_UP","timestamp":29541,"levelUpType":"NORMAL"},{"participantId":4,"skillSlot":1,"type":"SKILL_LEVEL_UP","timestamp":40544,"levelUpType":"NORMAL"},{"participantId":9,"skillSlot":2,"type":"SKILL_LEVEL_UP","timestamp":43285,"levelUpType":"NORMAL"},{"participantId":3,"skillSlot":1,"type":"SKILL_LEVEL_UP","timestamp":47318,"levelUpType":"NORMAL"}],"timestamp":60007},{"participantFrames":{"1":{"participantId":4,"minionsKilled":4,"teamScore":0,"dominionScore":0,"totalGold":597,"level":1,"xp":211,"currentGold":97,"position":{"x":2217,"y":13209},"jungleMinionsKilled":0},"2":{"participantId":5,"minionsKilled":0,"teamScore":0,"dominionScore":0,"totalGold":705,"level":2,"xp":475,"currentGold":205,"position":{"x":8555,"y":2791},"jungleMinionsKilled":8},"3":{"participantId":3,"minionsKilled":5,"teamScore":0,"dominionScore":0,"totalGold":611,"level":1,"xp":270,"currentGold":111,"position":{"x":6952,"y":7195},"jungleMinionsKilled":0},"4":{"participantId":2,"minionsKilled":3,"teamScore":0,"dominionScore":0,"totalGold":583,"level":1,"xp":113,"currentGold":83,"position":{"x":11832,"y":1673},"jungleMinionsKilled":0},"5":{"participantId":1,"minionsKilled":0,"teamScore":0,"dominionScore":0,"totalGold":522,"level":1,"xp":113,"currentGold":22,"position":{"x":12403,"y":1459},"jungleMinionsKilled":0},"6":{"participantId":7,"minionsKilled":2,"teamScore":0,"dominionScore":0,"totalGold":562,"level":1,"xp":181,"currentGold":62,"position":{"x":3184,"y":12949},"jungleMinionsKilled":0},"7":{"participantId":6,"minionsKilled":0,"teamScore":0,"dominionScore":0,"totalGold":620,"level":2,"xp":320,"currentGold":120,"position":{"x":11061,"y":7039},"jungleMinionsKilled":4},"8":{"participantId":10,"minionsKilled":5,"teamScore":0,"dominionScore":0,"totalGold":611,"level":1,"xp":240,"currentGold":111,"position":{"x":7984,"y":7618},"jungleMinionsKilled":0},"9":{"participantId":8,"minionsKilled":5,"teamScore":0,"dominionScore":0,"totalGold":611,"level":1,"xp":218,"currentGold":111,"position":{"x":12406,"y":2558},"jungleMinionsKilled":0},"10":{"participantId":9,"minionsKilled":0,"teamScore":0,"dominionScore":0,"totalGold":567,"level":1,"xp":37,"currentGold":67,"position":{"x":12951,"y":1735},"jungleMinionsKilled":0}},"events":[{"creatorId":9,"type":"WARD_PLACED","timestamp":74916,"wardType":"YELLOW_TRINKET"},{"creatorId":5,"type":"WARD_PLACED","timestamp":85852,"wardType":"YELLOW_TRINKET"},{"participantId":6,"skillSlot":2,"type":"SKILL_LEVEL_UP","timestamp":89719,"levelUpType":"NORMAL"},{"creatorId":4,"type":"WARD_PLACED","timestamp":98412,"wardType":"YELLOW_TRINKET"},{"participantId":5,"skillSlot":1,"type":"SKILL_LEVEL_UP","timestamp":104688,"levelUpType":"NORMAL"},{"participantId":6,"skillSlot":1,"type":"SKILL_LEVEL_UP","timestamp":107596,"levelUpType":"NORMAL"},{"participantId":7,"skillSlot":1,"type":"SKILL_LEVEL_UP","timestamp":115954,"levelUpType":"NORMAL"}],"timestamp":120017},{"participantFrames":{"1":{"participantId":4,"minionsKilled":17,"teamScore":0,"dominionScore":0,"totalGold":982,"level":3,"xp":904,"currentGold":482,"position":{"x":3877,"y":12797},"jungleMinionsKilled":0},"2":{"participantId":5,"minionsKilled":0,"teamScore":0,"dominionScore":0,"totalGold":1047,"level":3,"xp":865,"currentGold":547,"position":{"x":3757,"y":7806},"jungleMinionsKilled":16},"3":{"participantId":3,"minionsKilled":14,"teamScore":0,"dominionScore":0,"totalGold":940,"level":3,"xp":845,"currentGold":440,"position":{"x":6201,"y":8228},"jungleMinionsKilled":0},"4":{"participantId":2,"minionsKilled":12,"teamScore":0,"dominionScore":0,"totalGold":869,"level":2,"xp":431,"currentGold":369,"position":{"x":11655,"y":2035},"jungleMinionsKilled":0},"5":{"participantId":1,"minionsKilled":0,"teamScore":0,"dominionScore":0,"totalGold":661,"level":2,"xp":431,"currentGold":161,"position":{"x":11371,"y":1687},"jungleMinionsKilled":0},"6":{"participantId":7,"minionsKilled":8,"teamScore":0,"dominionScore":0,"totalGold":796,"level":2,"xp":512,"currentGold":296,"position":{"x":4274,"y":13713},"jungleMinionsKilled":0},"7":{"participantId":6,"minionsKilled":0,"teamScore":0,"dominionScore":0,"totalGold":947,"level":3,"xp":685,"currentGold":447,"position":{"x":7791,"y":7662},"jungleMinionsKilled":12},"8":{"participantId":10,"minionsKilled":11,"teamScore":0,"dominionScore":0,"totalGold":845,"level":3,"xp":662,"currentGold":345,"position":{"x":8073,"y":8129},"jungleMinionsKilled":0},"9":{"participantId":8,"minionsKilled":14,"teamScore":0,"dominionScore":0,"totalGold":933,"level":2,"xp":595,"currentGold":433,"position":{"x":12361,"y":2582},"jungleMinionsKilled":0},"10":{"participantId":9,"minionsKilled":0,"teamScore":0,"dominionScore":0,"totalGold":791,"level":2,"xp":414,"currentGold":291,"position":{"x":11957,"y":1493},"jungleMinionsKilled":0}},"events":[{"participantId":3,"skillSlot":2,"type":"SKILL_LEVEL_UP","timestamp":126920,"levelUpType":"NORMAL"},{"participantId":10,"skillSlot":3,"type":"SKILL_LEVEL_UP","timestamp":127251,"levelUpType":"NORMAL"},{"participantId":8,"skillSlot":3,"type":"SKILL_LEVEL_UP","timestamp":134684,"levelUpType":"NORMAL"},{"participantId":4,"skillSlot":2,"type":"SKILL_LEVEL_UP","timestamp":137130,"levelUpType":"NORMAL"},{"participantId":5,"skillSlot":3,"type":"SKILL_LEVEL_UP","timestamp":143143,"levelUpType":"NORMAL"},{"participantId":7,"skillSlot":2,"type":"SKILL_LEVEL_UP","timestamp":144332,"levelUpType":"NORMAL"},{"creatorId":3,"type":"WARD_PLACED","timestamp":146150,"wardType":"YELLOW_TRINKET"},{"participantId":1,"skillSlot":3,"type":"SKILL_LEVEL_UP","timestamp":153390,"levelUpType":"NORMAL"},{"participantId":2,"skillSlot":1,"type":"SKILL_LEVEL_UP","timestamp":153621,"levelUpType":"NORMAL"},{"participantId":6,"skillSlot":3,"type":"SKILL_LEVEL_UP","timestamp":157584,"levelUpType":"NORMAL"},{"participantId":3,"skillSlot":3,"type":"SKILL_LEVEL_UP","timestamp":158475,"levelUpType":"NORMAL"},{"participantId":4,"skillSlot":3,"type":"SKILL_LEVEL_UP","timestamp":166569,"levelUpType":"NORMAL"},{"participantId":10,"skillSlot":1,"type":"SKILL_LEVEL_UP","timestamp":166867,"levelUpType":"NORMAL"},{"participantId":9,"skillSlot":1,"type":"SKILL_LEVEL_UP","timestamp":167065,"levelUpType":"NORMAL"},{"creatorId":6,"type":"WARD_PLACED","timestamp":170071,"wardType":"YELLOW_TRINKET"},{"participantId":1,"itemId":2003,"type":"ITEM_DESTROYED","timestamp":175027}],"timestamp":180017},{"participantFrames":{"1":{"participantId":4,"minionsKilled":24,"teamScore":0,"dominionScore":0,"totalGold":1231,"level":4,"xp":1356,"currentGold":731,"position":{"x":2552,"y":12759},"jungleMinionsKilled":0},"2":{"participantId":5,"minionsKilled":0,"teamScore":0,"dominionScore":0,"totalGold":1452,"level":4,"xp":1416,"currentGold":952,"position":{"x":7793,"y":9677},"jungleMinionsKilled":28},"3":{"participantId":3,"minionsKilled":23,"teamScore":0,"dominionScore":0,"totalGold":1231,"level":4,"xp":1327,"currentGold":731,"position":{"x":6789,"y":8401},"jungleMinionsKilled":0},"4":{"participantId":2,"minionsKilled":23,"teamScore":0,"dominionScore":0,"totalGold":1198,"level":3,"xp":864,"currentGold":698,"position":{"x":11910,"y":1792},"jungleMinionsKilled":0},"5":{"participantId":1,"minionsKilled":0,"teamScore":0,"dominionScore":0,"totalGold":856,"level":3,"xp":864,"currentGold":356,"position":{"x":12473,"y":1411},"jungleMinionsKilled":0},"6":{"participantId":7,"minionsKilled":17,"teamScore":0,"dominionScore":0,"totalGold":1066,"level":4,"xp":1296,"currentGold":266,"position":{"x":3320,"y":13348},"jungleMinionsKilled":0},"7":{"participantId":6,"minionsKilled":0,"teamScore":0,"dominionScore":0,"totalGold":1162,"level":3,"xp":1094,"currentGold":662,"position":{"x":10780,"y":8812},"jungleMinionsKilled":17},"8":{"participantId":10,"minionsKilled":25,"teamScore":0,"dominionScore":0,"totalGold":1245,"level":4,"xp":1320,"currentGold":745,"position":{"x":7761,"y":7623},"jungleMinionsKilled":0},"9":{"participantId":8,"minionsKilled":20,"teamScore":0,"dominionScore":0,"totalGold":1168,"level":3,"xp":936,"currentGold":668,"position":{"x":12514,"y":2617},"jungleMinionsKilled":0},"10":{"participantId":9,"minionsKilled":0,"teamScore":0,"dominionScore":0,"totalGold":941,"level":3,"xp":696,"currentGold":441,"position":{"x":12928,"y":1947},"jungleMinionsKilled":0}},"events":[{"participantId":9,"itemId":2003,"type":"ITEM_DESTROYED","timestamp":183887},{"participantId":2,"itemId":2003,"type":"ITEM_DESTROYED","timestamp":185110},{"participantId":7,"skillSlot":3,"type":"SKILL_LEVEL_UP","timestamp":191356,"levelUpType":"NORMAL"},{"participantId":8,"skillSlot":2,"type":"SKILL_LEVEL_UP","timestamp":193271,"levelUpType":"NORMAL"},{"participantId":3,"itemId":2010,"type":"ITEM_DESTROYED","timestamp":194163},{"participantId":7,"itemId":2003,"type":"ITEM_DESTROYED","timestamp":194990},{"participantId":4,"itemId":2003,"type":"ITEM_DESTROYED","timestamp":197863},{"participantId":1,"skillSlot":2,"type":"SKILL_LEVEL_UP","timestamp":204932,"levelUpType":"NORMAL"},{"participantId":9,"itemId":2003,"type":"ITEM_DESTROYED","timestamp":205196},{"participantId":5,"skillSlot":3,"type":"SKILL_LEVEL_UP","timestamp":205295,"levelUpType":"NORMAL"},{"participantId":2,"skillSlot":2,"type":"SKILL_LEVEL_UP","timestamp":206486,"levelUpType":"NORMAL"},{"participantId":7,"itemId":1029,"type":"ITEM_PURCHASED","timestamp":212004},{"creatorId":1,"type":"WARD_PLACED","timestamp":215772,"wardType":"YELLOW_TRINKET"},{"participantId":4,"skillSlot":1,"type":"SKILL_LEVEL_UP","timestamp":216433,"levelUpType":"NORMAL"},{"participantId":7,"skillSlot":1,"type":"SKILL_LEVEL_UP","timestamp":217489,"levelUpType":"NORMAL"},{"creatorId":7,"type":"WARD_PLACED","timestamp":222149,"wardType":"YELLOW_TRINKET"},{"participantId":10,"itemId":2010,"type":"ITEM_DESTROYED","timestamp":222842},{"participantId":3,"skillSlot":1,"type":"SKILL_LEVEL_UP","timestamp":223602,"levelUpType":"NORMAL"},{"participantId":10,"skillSlot":2,"type":"SKILL_LEVEL_UP","timestamp":224626,"levelUpType":"NORMAL"},{"participantId":9,"skillSlot":2,"type":"SKILL_LEVEL_UP","timestamp":239661,"levelUpType":"NORMAL"}],"timestamp":240024},{"participantFrames":{"1":{"participantId":4,"minionsKilled":29,"teamScore":0,"dominionScore":0,"totalGold":1479,"level":5,"xp":1720,"currentGold":979,"position":{"x":1119,"y":10813},"jungleMinionsKilled":0},"2":{"participantId":5,"minionsKilled":0,"teamScore":0,"dominionScore":0,"totalGold":1704,"level":5,"xp":2037,"currentGold":1204,"position":{"x":6083,"y":6342},"jungleMinionsKilled":34},"3":{"participantId":3,"minionsKilled":28,"teamScore":0,"dominionScore":0,"totalGold":1486,"level":4,"xp":1712,"currentGold":986,"position":{"x":6687,"y":7156},"jungleMinionsKilled":0},"4":{"participantId":2,"minionsKilled":37,"teamScore":0,"dominionScore":0,"totalGold":1610,"level":4,"xp":1297,"currentGold":1110,"position":{"x":394,"y":461},"jungleMinionsKilled":0},"5":{"participantId":1,"minionsKilled":0,"teamScore":0,"dominionScore":0,"totalGold":1040,"level":4,"xp":1297,"currentGold":540,"position":{"x":13312,"y":2206},"jungleMinionsKilled":0},"6":{"participantId":7,"minionsKilled":28,"teamScore":0,"dominionScore":0,"totalGold":1819,"level":5,"xp":2066,"currentGold":1019,"position":{"x":2179,"y":12868},"jungleMinionsKilled":0},"7":{"participantId":6,"minionsKilled":0,"teamScore":0,"dominionScore":0,"totalGold":1614,"level":4,"xp":1525,"currentGold":1114,"position":{"x":1189,"y":12090},"jungleMinionsKilled":22},"8":{"participantId":10,"minionsKilled":33,"teamScore":0,"dominionScore":0,"totalGold":1849,"level":5,"xp":2108,"currentGold":1349,"position":{"x":6684,"y":8345},"jungleMinionsKilled":0},"9":{"participantId":8,"minionsKilled":28,"teamScore":0,"dominionScore":0,"totalGold":1479,"level":4,"xp":1306,"currentGold":979,"position":{"x":13871,"y":4308},"jungleMinionsKilled":0},"10":{"participantId":9,"minionsKilled":0,"teamScore":0,"dominionScore":0,"totalGold":1120,"level":3,"xp":885,"currentGold":620,"position":{"x":13109,"y":3751},"jungleMinionsKilled":0}},"events":[{"creatorId":8,"type":"WARD_PLACED","timestamp":242568,"wardType":"YELLOW_TRINKET"},{"participantId":6,"skillSlot":1,"type":"SKILL_LEVEL_UP","timestamp":247789,"levelUpType":"NORMAL"},{"creatorId":1,"type":"WARD_PLACED","timestamp":251061,"wardType":"YELLOW_TRINKET"},{"creatorId":4,"type":"WARD_PLACED","timestamp":252249,"wardType":"YELLOW_TRINKET"},{"participantId":4,"itemId":2010,"type":"ITEM_DESTROYED","timestamp":253736},{"participantId":1,"itemId":2003,"type":"ITEM_DESTROYED","timestamp":254595},{"participantId":8,"itemId":2010,"type":"ITEM_DESTROYED","timestamp":256477},{"participantId":2,"itemId":2010,"type":"ITEM_DESTROYED","timestamp":262790},{"participantId":7,"itemId":2010,"type":"ITEM_DESTROYED","timestamp":264276},{"participantId":8,"itemId":2003,"type":"ITEM_DESTROYED","timestamp":266819},{"participantId":7,"skillSlot":1,"type":"SKILL_LEVEL_UP","timestamp":270818,"levelUpType":"NORMAL"},{"participantId":4,"skillSlot":1,"type":"SKILL_LEVEL_UP","timestamp":273295,"levelUpType":"NORMAL"},{"creatorId":9,"type":"WARD_PLACED","timestamp":275541,"wardType":"YELLOW_TRINKET"},{"participantId":10,"skillSlot":1,"type":"SKILL_LEVEL_UP","timestamp":276995,"levelUpType":"NORMAL"},{"participantId":1,"skillSlot":3,"type":"SKILL_LEVEL_UP","timestamp":279505,"levelUpType":"NORMAL"},{"participantId":7,"itemId":2010,"type":"ITEM_DESTROYED","timestamp":279604},{"participantId":4,"itemId":2010,"type":"ITEM_DESTROYED","timestamp":279769},{"participantId":2,"skillSlot":1,"type":"SKILL_LEVEL_UP","timestamp":279769,"levelUpType":"NORMAL"},{"participantId":5,"skillSlot":3,"type":"SKILL_LEVEL_UP","timestamp":281123,"levelUpType":"NORMAL"},{"participantId":8,"skillSlot":2,"type":"SKILL_LEVEL_UP","timestamp":281156,"levelUpType":"NORMAL"},{"participantId":8,"itemId":2010,"type":"ITEM_DESTROYED","timestamp":282675},{"participantId":3,"itemId":2010,"type":"ITEM_DESTROYED","timestamp":286376},{"creatorId":6,"type":"WARD_PLACED","timestamp":287069,"wardType":"YELLOW_TRINKET"},{"creatorId":2,"type":"WARD_PLACED","timestamp":289282,"wardType":"YELLOW_TRINKET"},{"position":{"x":1119,"y":10813},"type":"CHAMPION_KILL","killerId":7,"timestamp":289645,"victimId":4,"assistingParticipantIds":[6]},{"position":{"x":6687,"y":7156},"type":"CHAMPION_KILL","killerId":10,"timestamp":289711,"victimId":3,"assistingParticipantIds":[]}],"timestamp":300027},{"participantFrames":{"1":{"participantId":4,"minionsKilled":33,"teamScore":0,"dominionScore":0,"totalGold":1680,"level":5,"xp":1992,"currentGold":230,"position":{"x":797,"y":5535},"jungleMinionsKilled":0},"2":{"participantId":5,"minionsKilled":6,"teamScore":0,"dominionScore":0,"totalGold":2383,"level":6,"xp":2799,"currentGold":708,"position":{"x":2162,"y":8758},"jungleMinionsKilled":34},"3":{"participantId":3,"minionsKilled":35,"teamScore":0,"dominionScore":0,"totalGold":1781,"level":5,"xp":2075,"currentGold":296,"position":{"x":8757,"y":4376},"jungleMinionsKilled":0},"4":{"participantId":2,"minionsKilled":41,"teamScore":0,"dominionScore":0,"totalGold":1811,"level":4,"xp":1598,"currentGold":211,"position":{"x":12739,"y":1778},"jungleMinionsKilled":0},"5":{"participantId":1,"minionsKilled":0,"teamScore":0,"dominionScore":0,"totalGold":1221,"level":4,"xp":1447,"currentGold":721,"position":{"x":12714,"y":1584},"jungleMinionsKilled":0},"6":{"participantId":7,"minionsKilled":35,"teamScore":0,"dominionScore":0,"totalGold":2350,"level":6,"xp":2836,"currentGold":225,"position":{"x":960,"y":11878},"jungleMinionsKilled":0},"7":{"participantId":6,"minionsKilled":0,"teamScore":0,"dominionScore":0,"totalGold":1843,"level":5,"xp":1748,"currentGold":268,"position":{"x":12691,"y":2026},"jungleMinionsKilled":26},"8":{"participantId":10,"minionsKilled":41,"teamScore":0,"dominionScore":0,"totalGold":2151,"level":6,"xp":2531,"currentGold":301,"position":{"x":7797,"y":7520},"jungleMinionsKilled":0},"9":{"participantId":8,"minionsKilled":43,"teamScore":0,"dominionScore":0,"totalGold":1862,"level":5,"xp":1749,"currentGold":1362,"position":{"x":13292,"y":3681},"jungleMinionsKilled":0},"10":{"participantId":9,"minionsKilled":1,"teamScore":0,"dominionScore":0,"totalGold":1345,"level":4,"xp":1298,"currentGold":845,"position":{"x":12983,"y":2565},"jungleMinionsKilled":0}},"events":[{"participantId":3,"itemId":1082,"type":"ITEM_PURCHASED","timestamp":300103},{"participantId":2,"itemId":3133,"type":"ITEM_PURCHASED","timestamp":301295},{"participantId":3,"itemId":1052,"type":"ITEM_PURCHASED","timestamp":302353},{"participantId":3,"itemId":2055,"type":"ITEM_PURCHASED","timestamp":303442},{"participantId":3,"itemId":1004,"type":"ITEM_PURCHASED","timestamp":303673},{"participantId":6,"itemId":3706,"type":"ITEM_PURCHASED","timestamp":304433},{"participantId":6,"itemId":1041,"type":"ITEM_DESTROYED","timestamp":304433},{"participantId":5,"itemId":3077,"type":"ITEM_PURCHASED","timestamp":305259},{"participantId":5,"itemId":1006,"type":"ITEM_DESTROYED","timestamp":305259},{"participantId":6,"itemId":1036,"type":"ITEM_PURCHASED","timestamp":305589},{"participantId":6,"itemId":2055,"type":"ITEM_PURCHASED","timestamp":305985},{"participantId":5,"itemId":3364,"type":"ITEM_PURCHASED","timestamp":306018},{"participantId":5,"itemId":3340,"type":"ITEM_DESTROYED","timestamp":306018},{"participantId":10,"itemId":1037,"type":"ITEM_PURCHASED","timestamp":306349},{"participantId":4,"itemId":2003,"type":"ITEM_PURCHASED","timestamp":306910},{"participantId":10,"itemId":1036,"type":"ITEM_PURCHASED","timestamp":307075},{"participantId":4,"itemId":1053,"type":"ITEM_PURCHASED","timestamp":307934},{"participantId":10,"itemId":1004,"type":"ITEM_PURCHASED","timestamp":309023},{"participantId":7,"itemId":3076,"type":"ITEM_PURCHASED","timestamp":310774},{"participantId":7,"itemId":1029,"type":"ITEM_DESTROYED","timestamp":310774},{"participantId":7,"itemId":2031,"type":"ITEM_PURCHASED","timestamp":311467},{"participantId":7,"itemId":2055,"type":"ITEM_PURCHASED","timestamp":311798},{"participantId":9,"skillSlot":3,"type":"SKILL_LEVEL_UP","timestamp":322403,"levelUpType":"NORMAL"},{"participantId":4,"itemId":2003,"type":"ITEM_DESTROYED","timestamp":325245},{"creatorId":3,"type":"WARD_PLACED","timestamp":332841,"wardType":"CONTROL_WARD"},{"participantId":3,"itemId":2055,"type":"ITEM_DESTROYED","timestamp":332841},{"creatorId":3,"type":"WARD_PLACED","timestamp":334096,"wardType":"YELLOW_TRINKET"},{"position":{"x":856,"y":10846},"type":"CHAMPION_KILL","killerId":7,"timestamp":334162,"victimId":4,"assistingParticipantIds":[]},{"participantId":7,"skillSlot":4,"type":"SKILL_LEVEL_UP","timestamp":335186,"levelUpType":"NORMAL"},{"participantId":3,"skillSlot":1,"type":"SKILL_LEVEL_UP","timestamp":338641,"levelUpType":"NORMAL"},{"participantId":6,"skillSlot":1,"type":"SKILL_LEVEL_UP","timestamp":343133,"levelUpType":"NORMAL"},{"creatorId":2,"type":"WARD_PLACED","timestamp":344124,"wardType":"YELLOW_TRINKET"},{"position":{"x":960,"y":11878},"type":"CHAMPION_KILL","killerId":5,"timestamp":348947,"victimId":7,"assistingParticipantIds":[]},{"participantId":10,"skillSlot":2,"type":"SKILL_LEVEL_UP","timestamp":353308,"levelUpType":"NORMAL"},{"participantId":8,"itemId":2003,"type":"ITEM_DESTROYED","timestamp":354927},{"participantId":5,"skillSlot":4,"type":"SKILL_LEVEL_UP","timestamp":355125,"levelUpType":"NORMAL"},{"participantId":7,"itemId":1028,"type":"ITEM_PURCHASED","timestamp":357603}],"timestamp":360046},{"participantFrames":{"1":{"participantId":4,"minionsKilled":40,"teamScore":0,"dominionScore":0,"totalGold":1928,"level":5,"xp":2323,"currentGold":478,"position":{"x":1129,"y":9010},"jungleMinionsKilled":0},"2":{"participantId":5,"minionsKilled":6,"teamScore":0,"dominionScore":0,"totalGold":2708,"level":7,"xp":3254,"currentGold":1033,"position":{"x":6686,"y":9443},"jungleMinionsKilled":42},"3":{"participantId":3,"minionsKilled":43,"teamScore":0,"dominionScore":0,"totalGold":2036,"level":5,"xp":2390,"currentGold":551,"position":{"x":7195,"y":6829},"jungleMinionsKilled":0},"4":{"participantId":2,"minionsKilled":53,"teamScore":0,"dominionScore":0,"totalGold":2150,"level":5,"xp":2382,"currentGold":550,"position":{"x":10348,"y":1310},"jungleMinionsKilled":0},"5":{"participantId":1,"minionsKilled":0,"teamScore":0,"dominionScore":0,"totalGold":1400,"level":4,"xp":1503,"currentGold":250,"position":{"x":8657,"y":4548},"jungleMinionsKilled":0},"6":{"participantId":7,"minionsKilled":43,"teamScore":0,"dominionScore":0,"totalGold":2605,"level":7,"xp":3196,"currentGold":480,"position":{"x":1766,"y":11316},"jungleMinionsKilled":0},"7":{"participantId":6,"minionsKilled":3,"teamScore":0,"dominionScore":0,"totalGold":2514,"level":5,"xp":2289,"currentGold":939,"position":{"x":7298,"y":11029},"jungleMinionsKilled":26},"8":{"participantId":10,"minionsKilled":47,"teamScore":0,"dominionScore":0,"totalGold":2838,"level":6,"xp":3045,"currentGold":988,"position":{"x":8791,"y":8606},"jungleMinionsKilled":0},"9":{"participantId":8,"minionsKilled":53,"teamScore":0,"dominionScore":0,"totalGold":2241,"level":5,"xp":2214,"currentGold":216,"position":{"x":11599,"y":1415},"jungleMinionsKilled":0},"10":{"participantId":9,"minionsKilled":1,"teamScore":0,"dominionScore":0,"totalGold":1584,"level":4,"xp":1550,"currentGold":84,"position":{"x":4200,"y":9218},"jungleMinionsKilled":0}},"events":[{"participantId":8,"skillSlot":2,"type":"SKILL_LEVEL_UP","timestamp":361037,"levelUpType":"NORMAL"},{"participantId":2,"itemId":2010,"type":"ITEM_DESTROYED","timestamp":361136},{"position":{"x":12360,"y":1324},"type":"CHAMPION_KILL","killerId":6,"timestamp":361930,"victimId":1,"assistingParticipantIds":[8,9]},{"participantId":8,"itemId":2010,"type":"ITEM_DESTROYED","timestamp":364309},{"participantId":2,"skillSlot":1,"type":"SKILL_LEVEL_UP","timestamp":368439,"levelUpType":"NORMAL"},{"participantId":2,"itemId":2010,"type":"ITEM_DESTROYED","timestamp":369165},{"participantId":1,"itemId":1001,"type":"ITEM_PURCHASED","timestamp":373262},{"participantId":1,"itemId":2031,"type":"ITEM_PURCHASED","timestamp":374418},{"participantId":1,"itemId":1004,"type":"ITEM_PURCHASED","timestamp":375244},{"participantId":1,"itemId":2055,"type":"ITEM_PURCHASED","timestamp":375574},{"creatorId":10,"type":"WARD_PLACED","timestamp":377357,"wardType":"YELLOW_TRINKET"},{"creatorId":8,"type":"WARD_PLACED","timestamp":382779,"wardType":"YELLOW_TRINKET"},{"participantId":5,"skillSlot":3,"type":"SKILL_LEVEL_UP","timestamp":385719,"levelUpType":"NORMAL"},{"participantId":8,"itemId":3802,"type":"ITEM_PURCHASED","timestamp":387835},{"participantId":8,"itemId":2031,"type":"ITEM_PURCHASED","timestamp":391039},{"participantId":8,"itemId":2055,"type":"ITEM_PURCHASED","timestamp":391534},{"participantId":9,"itemId":3117,"type":"ITEM_PURCHASED","timestamp":392260},{"creatorId":7,"type":"WARD_PLACED","timestamp":394937,"wardType":"CONTROL_WARD"},{"participantId":7,"itemId":2055,"type":"ITEM_DESTROYED","timestamp":394937},{"participantId":10,"itemId":2010,"type":"ITEM_DESTROYED","timestamp":398736},{"participantId":4,"itemId":2010,"type":"ITEM_DESTROYED","timestamp":403724},{"position":{"x":6686,"y":9443},"type":"CHAMPION_KILL","killerId":10,"timestamp":406961,"victimId":5,"assistingParticipantIds":[6]},{"participantId":10,"itemId":2010,"type":"ITEM_DESTROYED","timestamp":409044},{"participantId":7,"skillSlot":1,"type":"SKILL_LEVEL_UP","timestamp":419386,"levelUpType":"NORMAL"}],"timestamp":420079},{"participantFrames":{"1":{"participantId":4,"minionsKilled":40,"teamScore":0,"dominionScore":0,"totalGold":2050,"level":5,"xp":2383,"currentGold":100,"position":{"x":1051,"y":5856},"jungleMinionsKilled":0},"2":{"participantId":5,"minionsKilled":7,"teamScore":0,"dominionScore":0,"totalGold":3240,"level":7,"xp":3513,"currentGold":565,"position":{"x":12950,"y":2597},"jungleMinionsKilled":46},"3":{"participantId":3,"minionsKilled":53,"teamScore":0,"dominionScore":0,"totalGold":2340,"level":6,"xp":3024,"currentGold":855,"position":{"x":5789,"y":5524},"jungleMinionsKilled":0},"4":{"participantId":2,"minionsKilled":53,"teamScore":0,"dominionScore":0,"totalGold":2362,"level":6,"xp":2565,"currentGold":237,"position":{"x":12671,"y":2327},"jungleMinionsKilled":0},"5":{"participantId":1,"minionsKilled":2,"teamScore":0,"dominionScore":0,"totalGold":1699,"level":5,"xp":2042,"currentGold":549,"position":{"x":10596,"y":2250},"jungleMinionsKilled":0},"6":{"participantId":7,"minionsKilled":55,"teamScore":0,"dominionScore":0,"totalGold":3335,"level":7,"xp":3780,"currentGold":1210,"position":{"x":1168,"y":11517},"jungleMinionsKilled":0},"7":{"participantId":6,"minionsKilled":3,"teamScore":0,"dominionScore":0,"totalGold":2871,"level":6,"xp":2728,"currentGold":1296,"position":{"x":4690,"y":6882},"jungleMinionsKilled":34},"8":{"participantId":10,"minionsKilled":61,"teamScore":0,"dominionScore":0,"totalGold":3207,"level":7,"xp":3776,"currentGold":557,"position":{"x":7110,"y":7132},"jungleMinionsKilled":0},"9":{"participantId":8,"minionsKilled":62,"teamScore":0,"dominionScore":0,"totalGold":2959,"level":6,"xp":3056,"currentGold":934,"position":{"x":13629,"y":2697},"jungleMinionsKilled":0},"10":{"participantId":9,"minionsKilled":1,"teamScore":0,"dominionScore":0,"totalGold":2108,"level":5,"xp":1887,"currentGold":608,"position":{"x":4774,"y":6927},"jungleMinionsKilled":0}},"events":[{"participantId":3,"skillSlot":4,"type":"SKILL_LEVEL_UP","timestamp":422128,"levelUpType":"NORMAL"},{"participantId":5,"itemId":1001,"type":"ITEM_PURCHASED","timestamp":422327},{"participantId":5,"itemId":1036,"type":"ITEM_PURCHASED","timestamp":422723},{"participantId":5,"itemId":1036,"type":"ITEM_PURCHASED","timestamp":422822},{"participantId":10,"itemId":3070,"type":"ITEM_PURCHASED","timestamp":423945},{"participantId":10,"itemId":1004,"type":"ITEM_DESTROYED","timestamp":423945},{"participantId":10,"itemId":2055,"type":"ITEM_PURCHASED","timestamp":424970},{"participantId":6,"skillSlot":4,"type":"SKILL_LEVEL_UP","timestamp":426490,"levelUpType":"NORMAL"},{"participantId":2,"itemId":1055,"type":"ITEM_PURCHASED","timestamp":430060},{"participantId":2,"itemId":2055,"type":"ITEM_PURCHASED","timestamp":431252},{"participantId":8,"skillSlot":4,"type":"SKILL_LEVEL_UP","timestamp":437203,"levelUpType":"NORMAL"},{"participantId":9,"skillSlot":2,"type":"SKILL_LEVEL_UP","timestamp":443283,"levelUpType":"NORMAL"},{"creatorId":8,"type":"WARD_PLACED","timestamp":445167,"wardType":"CONTROL_WARD"},{"participantId":8,"itemId":2055,"type":"ITEM_DESTROYED","timestamp":445167},{"creatorId":3,"type":"WARD_PLACED","timestamp":445927,"wardType":"UNDEFINED"},{"participantId":10,"skillSlot":1,"type":"SKILL_LEVEL_UP","timestamp":446390,"levelUpType":"NORMAL"},{"position":{"x":763,"y":10118},"type":"CHAMPION_KILL","killerId":9,"timestamp":453394,"victimId":4,"assistingParticipantIds":[7]},{"participantId":1,"skillSlot":3,"type":"SKILL_LEVEL_UP","timestamp":457228,"levelUpType":"NORMAL"},{"participantId":4,"itemId":1036,"type":"ITEM_PURCHASED","timestamp":457327},{"participantId":4,"itemId":2031,"type":"ITEM_PURCHASED","timestamp":457525},{"participantId":2,"skillSlot":4,"type":"SKILL_LEVEL_UP","timestamp":462942,"levelUpType":"NORMAL"},{"creatorId":10,"type":"WARD_PLACED","timestamp":463008,"wardType":"CONTROL_WARD"},{"participantId":10,"itemId":2055,"type":"ITEM_DESTROYED","timestamp":463008},{"creatorId":8,"type":"WARD_PLACED","timestamp":470145,"wardType":"YELLOW_TRINKET"},{"type":"WARD_KILL","killerId":10,"timestamp":470145,"wardType":"CONTROL_WARD"},{"position":{"x":10596,"y":2250},"type":"CHAMPION_KILL","killerId":8,"timestamp":472094,"victimId":1,"assistingParticipantIds":[]},{"position":{"x":13629,"y":2697},"type":"CHAMPION_KILL","killerId":5,"timestamp":477742,"victimId":8,"assistingParticipantIds":[2,1]}],"timestamp":480088},{"participantFrames":{"1":{"participantId":4,"minionsKilled":48,"teamScore":0,"dominionScore":0,"totalGold":2320,"level":6,"xp":2835,"currentGold":370,"position":{"x":2394,"y":12106},"jungleMinionsKilled":0},"2":{"participantId":5,"minionsKilled":7,"teamScore":0,"dominionScore":0,"totalGold":3363,"level":7,"xp":3662,"currentGold":338,"position":{"x":2701,"y":5916},"jungleMinionsKilled":46},"3":{"participantId":3,"minionsKilled":57,"teamScore":0,"dominionScore":0,"totalGold":2584,"level":7,"xp":3213,"currentGold":234,"position":{"x":7660,"y":6907},"jungleMinionsKilled":0},"4":{"participantId":2,"minionsKilled":61,"teamScore":0,"dominionScore":0,"totalGold":2644,"level":6,"xp":2987,"currentGold":519,"position":{"x":7094,"y":7093},"jungleMinionsKilled":0},"5":{"participantId":1,"minionsKilled":2,"teamScore":0,"dominionScore":0,"totalGold":1834,"level":5,"xp":2171,"currentGold":284,"position":{"x":8623,"y":5614},"jungleMinionsKilled":0},"6":{"participantId":7,"minionsKilled":58,"teamScore":0,"dominionScore":0,"totalGold":3514,"level":7,"xp":3930,"currentGold":219,"position":{"x":2733,"y":12843},"jungleMinionsKilled":0},"7":{"participantId":6,"minionsKilled":5,"teamScore":0,"dominionScore":0,"totalGold":3798,"level":7,"xp":3352,"currentGold":2223,"position":{"x":7834,"y":9662},"jungleMinionsKilled":38},"8":{"participantId":10,"minionsKilled":71,"teamScore":0,"dominionScore":0,"totalGold":3776,"level":8,"xp":4509,"currentGold":451,"position":{"x":14314,"y":14368},"jungleMinionsKilled":0},"9":{"participantId":8,"minionsKilled":68,"teamScore":0,"dominionScore":0,"totalGold":3237,"level":7,"xp":3449,"currentGold":267,"position":{"x":11931,"y":2327},"jungleMinionsKilled":0},"10":{"participantId":9,"minionsKilled":1,"teamScore":0,"dominionScore":0,"totalGold":2502,"level":5,"xp":2157,"currentGold":67,"position":{"x":6634,"y":11413},"jungleMinionsKilled":0}},"events":[{"participantId":1,"itemId":1028,"type":"ITEM_PURCHASED","timestamp":481012},{"creatorId":6,"type":"WARD_PLACED","timestamp":485474,"wardType":"YELLOW_TRINKET"},{"position":{"x":6498,"y":6426},"type":"CHAMPION_KILL","killerId":6,"timestamp":488119,"victimId":3,"assistingParticipantIds":[10,9]},{"creatorId":7,"type":"WARD_PLACED","timestamp":489407,"wardType":"YELLOW_TRINKET"},{"participantId":10,"skillSlot":2,"type":"SKILL_LEVEL_UP","timestamp":490331,"levelUpType":"NORMAL"},{"participantId":8,"itemId":1052,"type":"ITEM_PURCHASED","timestamp":491190},{"participantId":8,"itemId":1052,"type":"ITEM_PURCHASED","timestamp":491421},{"participantId":7,"itemId":3751,"type":"ITEM_PURCHASED","timestamp":491520},{"participantId":7,"itemId":1028,"type":"ITEM_DESTROYED","timestamp":491520},{"participantId":8,"itemId":2055,"type":"ITEM_PURCHASED","timestamp":492181},{"participantId":7,"itemId":1028,"type":"ITEM_PURCHASED","timestamp":492643},{"participantId":7,"itemId":2010,"type":"ITEM_SOLD","timestamp":494129},{"participantId":7,"itemId":1029,"type":"ITEM_PURCHASED","timestamp":495219},{"participantId":3,"itemId":3802,"type":"ITEM_PURCHASED","timestamp":498129},{"participantId":3,"itemId":1052,"type":"ITEM_DESTROYED","timestamp":498129},{"creatorId":9,"type":"WARD_PLACED","timestamp":500872,"wardType":"YELLOW_TRINKET"},{"position":{"x":6263,"y":6390},"type":"CHAMPION_KILL","killerId":6,"timestamp":504508,"victimId":5,"assistingParticipantIds":[10,9]},{"creatorId":2,"type":"WARD_PLACED","timestamp":507812,"wardType":"CONTROL_WARD"},{"participantId":2,"itemId":2055,"type":"ITEM_DESTROYED","timestamp":507812},{"participantId":4,"skillSlot":4,"type":"SKILL_LEVEL_UP","timestamp":508110,"levelUpType":"NORMAL"},{"participantId":5,"itemId":1036,"type":"ITEM_PURCHASED","timestamp":508935},{"participantId":9,"itemId":3850,"type":"ITEM_DESTROYED","timestamp":509893},{"participantId":6,"skillSlot":1,"type":"SKILL_LEVEL_UP","timestamp":516238,"levelUpType":"NORMAL"},{"participantId":9,"itemId":1082,"type":"ITEM_PURCHASED","timestamp":517625},{"participantId":9,"itemId":1052,"type":"ITEM_PURCHASED","timestamp":517889},{"participantId":9,"itemId":2031,"type":"ITEM_PURCHASED","timestamp":517922},{"creatorId":2,"type":"WARD_PLACED","timestamp":518549,"wardType":"YELLOW_TRINKET"},{"creatorId":3,"type":"WARD_PLACED","timestamp":526244,"wardType":"UNDEFINED"},{"participantId":8,"skillSlot":2,"type":"SKILL_LEVEL_UP","timestamp":527862,"levelUpType":"NORMAL"},{"type":"WARD_KILL","killerId":2,"timestamp":533612,"wardType":"CONTROL_WARD"},{"participantId":3,"skillSlot":1,"type":"SKILL_LEVEL_UP","timestamp":534272,"levelUpType":"NORMAL"},{"creatorId":1,"type":"WARD_PLACED","timestamp":536818,"wardType":"YELLOW_TRINKET"},{"creatorId":3,"type":"WARD_PLACED","timestamp":537547,"wardType":"UNDEFINED"},{"participantId":10,"itemId":3004,"type":"ITEM_PURCHASED","timestamp":539730},{"participantId":10,"itemId":3070,"type":"ITEM_DESTROYED","timestamp":539730},{"participantId":10,"itemId":1037,"type":"ITEM_DESTROYED","timestamp":539730}],"timestamp":540093},{"participantFrames":{"1":{"participantId":4,"minionsKilled":50,"teamScore":0,"dominionScore":0,"totalGold":2477,"level":6,"xp":2986,"currentGold":177,"position":{"x":1297,"y":11193},"jungleMinionsKilled":0},"2":{"participantId":5,"minionsKilled":7,"teamScore":0,"dominionScore":0,"totalGold":3799,"level":8,"xp":4325,"currentGold":774,"position":{"x":6946,"y":5347},"jungleMinionsKilled":59},"3":{"participantId":3,"minionsKilled":63,"teamScore":0,"dominionScore":0,"totalGold":3111,"level":7,"xp":3653,"currentGold":386,"position":{"x":3818,"y":4248},"jungleMinionsKilled":0},"4":{"participantId":2,"minionsKilled":72,"teamScore":0,"dominionScore":0,"totalGold":2956,"level":7,"xp":3592,"currentGold":31,"position":{"x":1301,"y":659},"jungleMinionsKilled":0},"5":{"participantId":1,"minionsKilled":2,"teamScore":0,"dominionScore":0,"totalGold":2163,"level":6,"xp":2505,"currentGold":13,"position":{"x":3117,"y":1753},"jungleMinionsKilled":0},"6":{"participantId":7,"minionsKilled":70,"teamScore":0,"dominionScore":0,"totalGold":4146,"level":8,"xp":4651,"currentGold":851,"position":{"x":1261,"y":12266},"jungleMinionsKilled":0},"7":{"participantId":6,"minionsKilled":5,"teamScore":0,"dominionScore":0,"totalGold":4211,"level":7,"xp":3940,"currentGold":661,"position":{"x":10305,"y":4954},"jungleMinionsKilled":50},"8":{"participantId":10,"minionsKilled":79,"teamScore":0,"dominionScore":0,"totalGold":4278,"level":8,"xp":4877,"currentGold":528,"position":{"x":7422,"y":7312},"jungleMinionsKilled":0},"9":{"participantId":8,"minionsKilled":73,"teamScore":0,"dominionScore":0,"totalGold":3451,"level":7,"xp":3720,"currentGold":301,"position":{"x":13833,"y":10166},"jungleMinionsKilled":0},"10":{"participantId":9,"minionsKilled":1,"teamScore":0,"dominionScore":0,"totalGold":2966,"level":6,"xp":2553,"currentGold":531,"position":{"x":5812,"y":8511},"jungleMinionsKilled":0}},"events":[{"participantId":10,"itemId":1036,"type":"ITEM_PURCHASED","timestamp":541074},{"participantId":10,"itemId":2055,"type":"ITEM_PURCHASED","timestamp":541570},{"participantId":10,"itemId":3364,"type":"ITEM_PURCHASED","timestamp":543189},{"participantId":10,"itemId":3340,"type":"ITEM_DESTROYED","timestamp":543189},{"participantId":6,"itemId":1400,"type":"ITEM_PURCHASED","timestamp":543354},{"participantId":6,"itemId":1036,"type":"ITEM_DESTROYED","timestamp":543354},{"participantId":6,"itemId":3706,"type":"ITEM_DESTROYED","timestamp":543354},{"participantId":6,"itemId":1036,"type":"ITEM_PURCHASED","timestamp":544014},{"creatorId":7,"type":"WARD_PLACED","timestamp":545601,"wardType":"YELLOW_TRINKET"},{"participantId":6,"itemId":1036,"type":"ITEM_PURCHASED","timestamp":545634},{"creatorId":4,"type":"WARD_PLACED","timestamp":547320,"wardType":"YELLOW_TRINKET"},{"position":{"x":1231,"y":12525},"type":"CHAMPION_KILL","killerId":7,"timestamp":552077,"victimId":4,"assistingParticipantIds":[9]},{"participantId":7,"skillSlot":2,"type":"SKILL_LEVEL_UP","timestamp":554457,"levelUpType":"NORMAL"},{"creatorId":3,"type":"WARD_PLACED","timestamp":555415,"wardType":"YELLOW_TRINKET"},{"participantId":9,"skillSlot":4,"type":"SKILL_LEVEL_UP","timestamp":556837,"levelUpType":"NORMAL"},{"creatorId":9,"type":"WARD_PLACED","timestamp":557068,"wardType":"SIGHT_WARD"},{"participantId":4,"itemId":1036,"type":"ITEM_PURCHASED","timestamp":558026},{"participantId":2,"skillSlot":1,"type":"SKILL_LEVEL_UP","timestamp":567739,"levelUpType":"NORMAL"},{"creatorId":3,"type":"WARD_PLACED","timestamp":567871,"wardType":"UNDEFINED"},{"position":{"x":13243,"y":2628},"type":"CHAMPION_KILL","killerId":3,"timestamp":569853,"victimId":8,"assistingParticipantIds":[1]},{"participantId":1,"skillSlot":4,"type":"SKILL_LEVEL_UP","timestamp":570778,"levelUpType":"NORMAL"},{"participantId":3,"itemId":2010,"type":"ITEM_DESTROYED","timestamp":573421},{"creatorId":9,"type":"WARD_PLACED","timestamp":576493,"wardType":"SIGHT_WARD"},{"participantId":5,"skillSlot":1,"type":"SKILL_LEVEL_UP","timestamp":576956,"levelUpType":"NORMAL"},{"creatorId":9,"type":"WARD_PLACED","timestamp":582904,"wardType":"SIGHT_WARD"},{"participantId":3,"itemId":1001,"type":"ITEM_PURCHASED","timestamp":583003},{"participantId":8,"itemId":3145,"type":"ITEM_PURCHASED","timestamp":584027},{"participantId":8,"itemId":1052,"type":"ITEM_DESTROYED","timestamp":584027},{"participantId":8,"itemId":1052,"type":"ITEM_DESTROYED","timestamp":584027},{"participantId":3,"itemId":2055,"type":"ITEM_PURCHASED","timestamp":585018},{"participantId":1,"itemId":3364,"type":"ITEM_PURCHASED","timestamp":592254},{"participantId":1,"itemId":3340,"type":"ITEM_DESTROYED","timestamp":592254},{"participantId":1,"itemId":3158,"type":"ITEM_PURCHASED","timestamp":595263},{"participantId":1,"itemId":1001,"type":"ITEM_DESTROYED","timestamp":595263},{"participantId":2,"itemId":1018,"type":"ITEM_PURCHASED","timestamp":596916}],"timestamp":600094},{"participantFrames":{"1":{"participantId":4,"minionsKilled":58,"teamScore":0,"dominionScore":0,"totalGold":2787,"level":7,"xp":3529,"currentGold":487,"position":{"x":2092,"y":11797},"jungleMinionsKilled":0},"2":{"participantId":5,"minionsKilled":10,"teamScore":0,"dominionScore":0,"totalGold":4625,"level":8,"xp":4962,"currentGold":1600,"position":{"x":3358,"y":12882},"jungleMinionsKilled":66},"3":{"participantId":3,"minionsKilled":72,"teamScore":0,"dominionScore":0,"totalGold":3538,"level":8,"xp":4294,"currentGold":813,"position":{"x":4326,"y":11465},"jungleMinionsKilled":0},"4":{"participantId":2,"minionsKilled":83,"teamScore":0,"dominionScore":0,"totalGold":3606,"level":8,"xp":4605,"currentGold":681,"position":{"x":12548,"y":2436},"jungleMinionsKilled":0},"5":{"participantId":1,"minionsKilled":2,"teamScore":0,"dominionScore":0,"totalGold":2403,"level":6,"xp":2932,"currentGold":253,"position":{"x":6172,"y":10234},"jungleMinionsKilled":0},"6":{"participantId":7,"minionsKilled":78,"teamScore":0,"dominionScore":0,"totalGold":4535,"level":8,"xp":5008,"currentGold":740,"position":{"x":4013,"y":12607},"jungleMinionsKilled":0},"7":{"participantId":6,"minionsKilled":5,"teamScore":0,"dominionScore":0,"totalGold":4463,"level":8,"xp":4387,"currentGold":113,"position":{"x":5845,"y":10722},"jungleMinionsKilled":58},"8":{"participantId":10,"minionsKilled":85,"teamScore":0,"dominionScore":0,"totalGold":4559,"level":9,"xp":5240,"currentGold":109,"position":{"x":8449,"y":7876},"jungleMinionsKilled":0},"9":{"participantId":8,"minionsKilled":82,"teamScore":0,"dominionScore":0,"totalGold":3788,"level":8,"xp":4173,"currentGold":188,"position":{"x":12550,"y":2702},"jungleMinionsKilled":0},"10":{"participantId":9,"minionsKilled":2,"teamScore":0,"dominionScore":0,"totalGold":3297,"level":6,"xp":2972,"currentGold":862,"position":{"x":4291,"y":12381},"jungleMinionsKilled":0}},"events":[{"participantId":7,"itemId":1031,"type":"ITEM_PURCHASED","timestamp":601614},{"participantId":7,"itemId":1029,"type":"ITEM_DESTROYED","timestamp":601614},{"participantId":10,"skillSlot":1,"type":"SKILL_LEVEL_UP","timestamp":604357,"levelUpType":"NORMAL"},{"monsterType":"DRAGON","monsterSubType":"AIR_DRAGON","position":{"x":10502,"y":5032},"type":"ELITE_MONSTER_KILL","killerId":6,"timestamp":606142},{"participantId":6,"skillSlot":2,"type":"SKILL_LEVEL_UP","timestamp":607562,"levelUpType":"NORMAL"},{"creatorId":3,"type":"WARD_PLACED","timestamp":617405,"wardType":"UNDEFINED"},{"position":{"x":8449,"y":7876},"type":"CHAMPION_KILL","killerId":5,"timestamp":630722,"victimId":10,"assistingParticipantIds":[3,1]},{"participantId":6,"itemId":3134,"type":"ITEM_PURCHASED","timestamp":630986},{"participantId":6,"itemId":1036,"type":"ITEM_DESTROYED","timestamp":630986},{"participantId":6,"itemId":1036,"type":"ITEM_DESTROYED","timestamp":630986},{"participantId":6,"itemId":1028,"type":"ITEM_PURCHASED","timestamp":631085},{"creatorId":3,"type":"WARD_PLACED","timestamp":631118,"wardType":"UNDEFINED"},{"participantId":3,"skillSlot":3,"type":"SKILL_LEVEL_UP","timestamp":634093,"levelUpType":"NORMAL"},{"participantId":10,"itemId":3134,"type":"ITEM_PURCHASED","timestamp":634887},{"participantId":10,"itemId":1036,"type":"ITEM_DESTROYED","timestamp":634887},{"participantId":10,"itemId":1036,"type":"ITEM_DESTROYED","timestamp":634887},{"creatorId":3,"type":"WARD_PLACED","timestamp":639579,"wardType":"CONTROL_WARD"},{"participantId":3,"itemId":2055,"type":"ITEM_DESTROYED","timestamp":639579},{"position":{"x":12550,"y":2702},"type":"CHAMPION_KILL","killerId":2,"timestamp":641430,"victimId":8,"assistingParticipantIds":[]},{"participantId":8,"skillSlot":1,"type":"SKILL_LEVEL_UP","timestamp":642090,"levelUpType":"NORMAL"},{"participantId":4,"skillSlot":1,"type":"SKILL_LEVEL_UP","timestamp":646253,"levelUpType":"NORMAL"},{"participantId":2,"skillSlot":3,"type":"SKILL_LEVEL_UP","timestamp":646947,"levelUpType":"NORMAL"},{"participantId":10,"itemId":1001,"type":"ITEM_PURCHASED","timestamp":649095},{"participantId":8,"itemId":3030,"type":"ITEM_PURCHASED","timestamp":650977},{"participantId":8,"itemId":3802,"type":"ITEM_DESTROYED","timestamp":650977},{"participantId":8,"itemId":3145,"type":"ITEM_DESTROYED","timestamp":650977},{"creatorId":3,"type":"WARD_PLACED","timestamp":655600,"wardType":"UNDEFINED"},{"creatorId":6,"type":"WARD_PLACED","timestamp":658611,"wardType":"YELLOW_TRINKET"}],"timestamp":660098},{"participantFrames":{"1":{"participantId":4,"minionsKilled":59,"teamScore":0,"dominionScore":0,"totalGold":2930,"level":7,"xp":3680,"currentGold":5,"position":{"x":400,"y":491},"jungleMinionsKilled":0},"2":{"participantId":5,"minionsKilled":10,"teamScore":0,"dominionScore":0,"totalGold":4747,"level":8,"xp":4962,"currentGold":222,"position":{"x":1241,"y":908},"jungleMinionsKilled":66},"3":{"participantId":3,"minionsKilled":72,"teamScore":0,"dominionScore":0,"totalGold":3660,"level":8,"xp":4294,"currentGold":97,"position":{"x":4237,"y":4401},"jungleMinionsKilled":0},"4":{"participantId":2,"minionsKilled":89,"teamScore":0,"dominionScore":0,"totalGold":3833,"level":8,"xp":4876,"currentGold":908,"position":{"x":5306,"y":5270},"jungleMinionsKilled":0},"5":{"participantId":1,"minionsKilled":2,"teamScore":0,"dominionScore":0,"totalGold":2582,"level":6,"xp":2932,"currentGold":182,"position":{"x":3727,"y":2036},"jungleMinionsKilled":0},"6":{"participantId":7,"minionsKilled":79,"teamScore":0,"dominionScore":0,"totalGold":4763,"level":9,"xp":5216,"currentGold":243,"position":{"x":3437,"y":13337},"jungleMinionsKilled":0},"7":{"participantId":6,"minionsKilled":6,"teamScore":0,"dominionScore":0,"totalGold":5256,"level":8,"xp":5009,"currentGold":906,"position":{"x":4738,"y":10141},"jungleMinionsKilled":62},"8":{"participantId":10,"minionsKilled":95,"teamScore":0,"dominionScore":0,"totalGold":5592,"level":9,"xp":5794,"currentGold":1142,"position":{"x":6584,"y":7183},"jungleMinionsKilled":0},"9":{"participantId":8,"minionsKilled":88,"teamScore":0,"dominionScore":0,"totalGold":4282,"level":8,"xp":4597,"currentGold":682,"position":{"x":11071,"y":1197},"jungleMinionsKilled":0},"10":{"participantId":9,"minionsKilled":2,"teamScore":0,"dominionScore":0,"totalGold":4153,"level":7,"xp":3454,"currentGold":1718,"position":{"x":4125,"y":7345},"jungleMinionsKilled":0}},"events":[{"participantId":7,"itemId":3068,"type":"ITEM_PURCHASED","timestamp":671909},{"participantId":7,"itemId":1031,"type":"ITEM_DESTROYED","timestamp":671909},{"participantId":7,"itemId":1028,"type":"ITEM_DESTROYED","timestamp":671909},{"participantId":7,"itemId":3751,"type":"ITEM_DESTROYED","timestamp":671909},{"creatorId":9,"type":"WARD_PLACED","timestamp":674684,"wardType":"YELLOW_TRINKET"},{"position":{"x":2825,"y":10060},"type":"CHAMPION_KILL","killerId":6,"timestamp":680204,"victimId":3,"assistingParticipantIds":[9]},{"participantId":9,"skillSlot":3,"type":"SKILL_LEVEL_UP","timestamp":681791,"levelUpType":"NORMAL"},{"participantId":7,"skillSlot":1,"type":"SKILL_LEVEL_UP","timestamp":685690,"levelUpType":"NORMAL"},{"participantId":3,"itemId":1026,"type":"ITEM_PURCHASED","timestamp":686648},{"creatorId":6,"type":"WARD_PLACED","timestamp":689060,"wardType":"CONTROL_WARD"},{"participantId":6,"itemId":2055,"type":"ITEM_DESTROYED","timestamp":689060},{"creatorId":4,"type":"WARD_PLACED","timestamp":690778,"wardType":"YELLOW_TRINKET"},{"position":{"x":3635,"y":8331},"type":"CHAMPION_KILL","killerId":9,"timestamp":693684,"victimId":1,"assistingParticipantIds":[6,10]},{"position":{"x":1504,"y":9766},"type":"CHAMPION_KILL","killerId":9,"timestamp":698210,"victimId":4,"assistingParticipantIds":[7,6]},{"type":"WARD_KILL","killerId":7,"timestamp":702044,"wardType":"YELLOW_TRINKET"},{"participantId":3,"itemId":1004,"type":"ITEM_SOLD","timestamp":702671},{"participantId":3,"itemId":1004,"type":"ITEM_PURCHASED","timestamp":703035},{"participantId":3,"beforeId":1004,"afterId":0,"type":"ITEM_UNDO","timestamp":704390},{"participantId":3,"itemId":2055,"type":"ITEM_PURCHASED","timestamp":705646},{"participantId":7,"itemId":2055,"type":"ITEM_PURCHASED","timestamp":711001},{"laneType":"MID_LANE","towerType":"OUTER_TURRET","teamId":100,"position":{"x":5846,"y":6396},"type":"BUILDING_KILL","killerId":10,"timestamp":712157,"assistingParticipantIds":[],"buildingType":"TOWER_BUILDING"},{"participantId":1,"itemId":3801,"type":"ITEM_PURCHASED","timestamp":714670},{"participantId":1,"itemId":1028,"type":"ITEM_DESTROYED","timestamp":714670},{"participantId":5,"itemId":3134,"type":"ITEM_PURCHASED","timestamp":717149},{"participantId":5,"itemId":1036,"type":"ITEM_DESTROYED","timestamp":717149},{"participantId":5,"itemId":1036,"type":"ITEM_DESTROYED","timestamp":717149},{"participantId":5,"itemId":3133,"type":"ITEM_PURCHASED","timestamp":718569},{"participantId":5,"itemId":1036,"type":"ITEM_DESTROYED","timestamp":718569},{"participantId":4,"itemId":3077,"type":"ITEM_PURCHASED","timestamp":719461},{"participantId":4,"itemId":1036,"type":"ITEM_DESTROYED","timestamp":719461},{"participantId":4,"itemId":1036,"type":"ITEM_DESTROYED","timestamp":719461},{"participantId":5,"itemId":1036,"type":"ITEM_PURCHASED","timestamp":719824}],"timestamp":720121},{"participantFrames":{"1":{"participantId":4,"minionsKilled":69,"teamScore":0,"dominionScore":0,"totalGold":3199,"level":8,"xp":4068,"currentGold":274,"position":{"x":1061,"y":9003},"jungleMinionsKilled":0},"2":{"participantId":5,"minionsKilled":10,"teamScore":0,"dominionScore":0,"totalGold":5071,"level":9,"xp":5375,"currentGold":546,"position":{"x":8497,"y":2350},"jungleMinionsKilled":73},"3":{"participantId":3,"minionsKilled":78,"teamScore":0,"dominionScore":0,"totalGold":3902,"level":8,"xp":4714,"currentGold":340,"position":{"x":9156,"y":3413},"jungleMinionsKilled":0},"4":{"participantId":2,"minionsKilled":104,"teamScore":0,"dominionScore":0,"totalGold":4265,"level":9,"xp":5600,"currentGold":1340,"position":{"x":12231,"y":1271},"jungleMinionsKilled":0},"5":{"participantId":1,"minionsKilled":2,"teamScore":0,"dominionScore":0,"totalGold":2731,"level":6,"xp":2932,"currentGold":331,"position":{"x":8860,"y":2231},"jungleMinionsKilled":0},"6":{"participantId":7,"minionsKilled":95,"teamScore":0,"dominionScore":0,"totalGold":5675,"level":9,"xp":6000,"currentGold":355,"position":{"x":1076,"y":9505},"jungleMinionsKilled":0},"7":{"participantId":6,"minionsKilled":6,"teamScore":0,"dominionScore":0,"totalGold":5732,"level":9,"xp":5716,"currentGold":1382,"position":{"x":3674,"y":9346},"jungleMinionsKilled":74},"8":{"participantId":10,"minionsKilled":106,"teamScore":0,"dominionScore":0,"totalGold":5972,"level":10,"xp":6320,"currentGold":422,"position":{"x":7343,"y":7462},"jungleMinionsKilled":0},"9":{"participantId":8,"minionsKilled":98,"teamScore":0,"dominionScore":0,"totalGold":4783,"level":8,"xp":5032,"currentGold":1183,"position":{"x":12739,"y":2429},"jungleMinionsKilled":0},"10":{"participantId":9,"minionsKilled":2,"teamScore":0,"dominionScore":0,"totalGold":4343,"level":7,"xp":3529,"currentGold":168,"position":{"x":10687,"y":5415},"jungleMinionsKilled":0}},"events":[{"participantId":9,"itemId":3364,"type":"ITEM_PURCHASED","timestamp":721972},{"participantId":9,"itemId":3340,"type":"ITEM_DESTROYED","timestamp":721972},{"participantId":9,"itemId":2055,"type":"ITEM_PURCHASED","timestamp":722632},{"type":"WARD_KILL","killerId":10,"timestamp":725176,"wardType":"CONTROL_WARD"},{"participantId":2,"skillSlot":1,"type":"SKILL_LEVEL_UP","timestamp":726893,"levelUpType":"NORMAL"},{"participantId":9,"itemId":3174,"type":"ITEM_PURCHASED","timestamp":729602},{"participantId":9,"itemId":1052,"type":"ITEM_DESTROYED","timestamp":729602},{"participantId":10,"itemId":3133,"type":"ITEM_PURCHASED","timestamp":735486},{"monsterType":"RIFTHERALD","position":{"x":4558,"y":10042},"type":"ELITE_MONSTER_KILL","killerId":6,"timestamp":742227},{"participantId":6,"skillSlot":1,"type":"SKILL_LEVEL_UP","timestamp":743019,"levelUpType":"NORMAL"},{"participantId":6,"itemId":3340,"type":"ITEM_DESTROYED","timestamp":743812},{"laneType":"TOP_LANE","towerType":"OUTER_TURRET","teamId":100,"position":{"x":981,"y":10441},"type":"BUILDING_KILL","killerId":7,"timestamp":744572,"assistingParticipantIds":[],"buildingType":"TOWER_BUILDING"},{"participantId":5,"skillSlot":3,"type":"SKILL_LEVEL_UP","timestamp":744605,"levelUpType":"NORMAL"},{"creatorId":3,"type":"WARD_PLACED","timestamp":750418,"wardType":"YELLOW_TRINKET"},{"creatorId":3,"type":"WARD_PLACED","timestamp":754449,"wardType":"UNDEFINED"},{"creatorId":1,"type":"WARD_PLACED","timestamp":757422,"wardType":"CONTROL_WARD"},{"participantId":1,"itemId":2055,"type":"ITEM_DESTROYED","timestamp":757422},{"creatorId":9,"type":"WARD_PLACED","timestamp":757819,"wardType":"SIGHT_WARD"},{"creatorId":8,"type":"WARD_PLACED","timestamp":759900,"wardType":"CONTROL_WARD"},{"participantId":8,"itemId":2055,"type":"ITEM_DESTROYED","timestamp":759900},{"creatorId":2,"type":"WARD_PLACED","timestamp":760494,"wardType":"YELLOW_TRINKET"},{"participantId":7,"itemId":3047,"type":"ITEM_PURCHASED","timestamp":762577},{"participantId":7,"itemId":2422,"type":"ITEM_DESTROYED","timestamp":762577},{"creatorId":8,"type":"WARD_PLACED","timestamp":764428,"wardType":"YELLOW_TRINKET"},{"creatorId":9,"type":"WARD_PLACED","timestamp":768760,"wardType":"SIGHT_WARD"},{"type":"WARD_KILL","killerId":10,"timestamp":769389,"wardType":"YELLOW_TRINKET"},{"participantId":10,"skillSlot":2,"type":"SKILL_LEVEL_UP","timestamp":769984,"levelUpType":"NORMAL"}],"timestamp":780130},{"participantFrames":{"1":{"participantId":4,"minionsKilled":77,"teamScore":0,"dominionScore":0,"totalGold":3508,"level":8,"xp":4521,"currentGold":583,"position":{"x":1198,"y":8075},"jungleMinionsKilled":0},"2":{"participantId":5,"minionsKilled":10,"teamScore":0,"dominionScore":0,"totalGold":5212,"level":9,"xp":5485,"currentGold":687,"position":{"x":2867,"y":3809},"jungleMinionsKilled":74},"3":{"participantId":3,"minionsKilled":84,"teamScore":0,"dominionScore":0,"totalGold":4190,"level":8,"xp":4964,"currentGold":627,"position":{"x":5220,"y":4909},"jungleMinionsKilled":0},"4":{"participantId":2,"minionsKilled":115,"teamScore":0,"dominionScore":0,"totalGold":4591,"level":10,"xp":6124,"currentGold":191,"position":{"x":3693,"y":3479},"jungleMinionsKilled":0},"5":{"participantId":1,"minionsKilled":2,"teamScore":0,"dominionScore":0,"totalGold":2911,"level":7,"xp":3289,"currentGold":386,"position":{"x":3957,"y":3438},"jungleMinionsKilled":0},"6":{"participantId":7,"minionsKilled":105,"teamScore":0,"dominionScore":0,"totalGold":6602,"level":10,"xp":6617,"currentGold":1282,"position":{"x":4899,"y":5482},"jungleMinionsKilled":0},"7":{"participantId":6,"minionsKilled":8,"teamScore":0,"dominionScore":0,"totalGold":6490,"level":10,"xp":6159,"currentGold":2140,"position":{"x":4015,"y":4423},"jungleMinionsKilled":78},"8":{"participantId":10,"minionsKilled":116,"teamScore":0,"dominionScore":0,"totalGold":6524,"level":10,"xp":6891,"currentGold":974,"position":{"x":3808,"y":4415},"jungleMinionsKilled":0},"9":{"participantId":8,"minionsKilled":111,"teamScore":0,"dominionScore":0,"totalGold":5262,"level":9,"xp":5703,"currentGold":1662,"position":{"x":11140,"y":1234},"jungleMinionsKilled":0},"10":{"participantId":9,"minionsKilled":3,"teamScore":0,"dominionScore":0,"totalGold":4774,"level":7,"xp":3848,"currentGold":599,"position":{"x":3837,"y":4313},"jungleMinionsKilled":0}},"events":[{"creatorId":9,"type":"WARD_PLACED","timestamp":782868,"wardType":"SIGHT_WARD"},{"participantId":4,"skillSlot":3,"type":"SKILL_LEVEL_UP","timestamp":783694,"levelUpType":"NORMAL"},{"creatorId":10,"type":"WARD_PLACED","timestamp":786272,"wardType":"CONTROL_WARD"},{"participantId":10,"itemId":2055,"type":"ITEM_DESTROYED","timestamp":786272},{"creatorId":3,"type":"WARD_PLACED","timestamp":786404,"wardType":"CONTROL_WARD"},{"participantId":3,"itemId":2055,"type":"ITEM_DESTROYED","timestamp":786404},{"participantId":7,"skillSlot":2,"type":"SKILL_LEVEL_UP","timestamp":789541,"levelUpType":"NORMAL"},{"participantId":8,"skillSlot":2,"type":"SKILL_LEVEL_UP","timestamp":790929,"levelUpType":"NORMAL"},{"position":{"x":5603,"y":6147},"type":"CHAMPION_KILL","killerId":6,"timestamp":808051,"victimId":1,"assistingParticipantIds":[7]},{"creatorId":3,"type":"WARD_PLACED","timestamp":811158,"wardType":"UNDEFINED"},{"type":"WARD_KILL","killerId":8,"timestamp":812149,"wardType":"CONTROL_WARD"},{"position":{"x":5220,"y":4909},"type":"CHAMPION_KILL","killerId":7,"timestamp":813206,"victimId":3,"assistingParticipantIds":[6,10,9]},{"creatorId":7,"type":"WARD_PLACED","timestamp":815815,"wardType":"YELLOW_TRINKET"},{"participantId":6,"itemId":3513,"type":"ITEM_DESTROYED","timestamp":816640},{"participantId":2,"itemId":3508,"type":"ITEM_PURCHASED","timestamp":818887},{"participantId":2,"itemId":3133,"type":"ITEM_DESTROYED","timestamp":818887},{"participantId":2,"itemId":1018,"type":"ITEM_DESTROYED","timestamp":818887},{"participantId":2,"itemId":3363,"type":"ITEM_PURCHASED","timestamp":819977},{"participantId":2,"itemId":3340,"type":"ITEM_DESTROYED","timestamp":819977},{"participantId":2,"itemId":2055,"type":"ITEM_PURCHASED","timestamp":820373},{"type":"WARD_KILL","killerId":6,"timestamp":822454,"wardType":"CONTROL_WARD"},{"participantId":1,"itemId":1004,"type":"ITEM_PURCHASED","timestamp":826284},{"laneType":"MID_LANE","towerType":"INNER_TURRET","teamId":100,"position":{"x":5048,"y":4812},"type":"BUILDING_KILL","killerId":6,"timestamp":828564,"assistingParticipantIds":[7,9],"buildingType":"TOWER_BUILDING"},{"participantId":6,"skillSlot":2,"type":"SKILL_LEVEL_UP","timestamp":832166,"levelUpType":"NORMAL"}],"timestamp":840163},{"participantFrames":{"1":{"participantId":4,"minionsKilled":77,"teamScore":0,"dominionScore":0,"totalGold":3630,"level":8,"xp":4582,"currentGold":355,"position":{"x":394,"y":461},"jungleMinionsKilled":0},"2":{"participantId":5,"minionsKilled":10,"teamScore":0,"dominionScore":0,"totalGold":5419,"level":9,"xp":5698,"currentGold":194,"position":{"x":3833,"y":7802},"jungleMinionsKilled":78},"3":{"participantId":3,"minionsKilled":89,"teamScore":0,"dominionScore":0,"totalGold":4412,"level":9,"xp":5157,"currentGold":250,"position":{"x":7774,"y":5781},"jungleMinionsKilled":0},"4":{"participantId":2,"minionsKilled":128,"teamScore":0,"dominionScore":0,"totalGold":4994,"level":10,"xp":6728,"currentGold":594,"position":{"x":8208,"y":2098},"jungleMinionsKilled":0},"5":{"participantId":1,"minionsKilled":2,"teamScore":0,"dominionScore":0,"totalGold":3051,"level":7,"xp":3348,"currentGold":526,"position":{"x":8766,"y":5443},"jungleMinionsKilled":0},"6":{"participantId":7,"minionsKilled":108,"teamScore":0,"dominionScore":0,"totalGold":7071,"level":10,"xp":6996,"currentGold":681,"position":{"x":1331,"y":10471},"jungleMinionsKilled":4},"7":{"participantId":6,"minionsKilled":8,"teamScore":0,"dominionScore":0,"totalGold":6830,"level":10,"xp":6387,"currentGold":2480,"position":{"x":12142,"y":1289},"jungleMinionsKilled":78},"8":{"participantId":10,"minionsKilled":117,"teamScore":0,"dominionScore":0,"totalGold":6865,"level":10,"xp":7079,"currentGold":15,"position":{"x":12951,"y":11579},"jungleMinionsKilled":0},"9":{"participantId":8,"minionsKilled":122,"teamScore":0,"dominionScore":0,"totalGold":5918,"level":10,"xp":6175,"currentGold":18,"position":{"x":12305,"y":11202},"jungleMinionsKilled":0},"10":{"participantId":9,"minionsKilled":3,"teamScore":0,"dominionScore":0,"totalGold":5142,"level":7,"xp":4007,"currentGold":167,"position":{"x":14003,"y":13667},"jungleMinionsKilled":0}},"events":[{"participantId":7,"itemId":2055,"type":"ITEM_SOLD","timestamp":840889},{"laneType":"MID_LANE","towerType":"BASE_TURRET","teamId":100,"position":{"x":3651,"y":3696},"type":"BUILDING_KILL","killerId":10,"timestamp":841583,"assistingParticipantIds":[6],"buildingType":"TOWER_BUILDING"},{"participantId":7,"itemId":3010,"type":"ITEM_PURCHASED","timestamp":841847},{"participantId":2,"skillSlot":3,"type":"SKILL_LEVEL_UP","timestamp":842408,"levelUpType":"NORMAL"},{"participantId":1,"skillSlot":2,"type":"SKILL_LEVEL_UP","timestamp":843235,"levelUpType":"NORMAL"},{"participantId":3,"itemId":3158,"type":"ITEM_PURCHASED","timestamp":843863},{"participantId":3,"itemId":1001,"type":"ITEM_DESTROYED","timestamp":843863},{"participantId":1,"itemId":3850,"type":"ITEM_DESTROYED","timestamp":845581},{"participantId":4,"itemId":1036,"type":"ITEM_PURCHASED","timestamp":852254},{"participantId":5,"itemId":3147,"type":"ITEM_PURCHASED","timestamp":854269},{"participantId":5,"itemId":3134,"type":"ITEM_DESTROYED","timestamp":854269},{"participantId":5,"itemId":3133,"type":"ITEM_DESTROYED","timestamp":854269},{"participantId":3,"skillSlot":1,"type":"SKILL_LEVEL_UP","timestamp":854566,"levelUpType":"NORMAL"},{"position":{"x":11228,"y":1901},"type":"CHAMPION_KILL","killerId":8,"timestamp":864181,"victimId":4,"assistingParticipantIds":[6,10,9]},{"laneType":"BOT_LANE","towerType":"OUTER_TURRET","teamId":100,"position":{"x":10504,"y":1029},"type":"BUILDING_KILL","killerId":10,"timestamp":867287,"assistingParticipantIds":[6,8,9],"buildingType":"TOWER_BUILDING"},{"creatorId":3,"type":"WARD_PLACED","timestamp":869865,"wardType":"UNDEFINED"},{"creatorId":1,"type":"WARD_PLACED","timestamp":873136,"wardType":"SIGHT_WARD"},{"participantId":8,"skillSlot":1,"type":"SKILL_LEVEL_UP","timestamp":873236,"levelUpType":"NORMAL"},{"creatorId":8,"type":"WARD_PLACED","timestamp":876477,"wardType":"YELLOW_TRINKET"},{"participantId":9,"itemId":3851,"type":"ITEM_DESTROYED","timestamp":877304},{"creatorId":9,"type":"WARD_PLACED","timestamp":883516,"wardType":"CONTROL_WARD"},{"participantId":9,"itemId":2055,"type":"ITEM_DESTROYED","timestamp":883516},{"creatorId":3,"type":"WARD_PLACED","timestamp":886125,"wardType":"UNDEFINED"},{"participantId":8,"itemId":3136,"type":"ITEM_PURCHASED","timestamp":886719},{"participantId":10,"itemId":3142,"type":"ITEM_PURCHASED","timestamp":889726},{"participantId":10,"itemId":3133,"type":"ITEM_DESTROYED","timestamp":889726},{"participantId":10,"itemId":3134,"type":"ITEM_DESTROYED","timestamp":889726},{"type":"WARD_KILL","killerId":3,"timestamp":890815,"wardType":"CONTROL_WARD"},{"participantId":8,"itemId":3020,"type":"ITEM_PURCHASED","timestamp":892698},{"participantId":8,"itemId":2422,"type":"ITEM_DESTROYED","timestamp":892698},{"participantId":10,"itemId":3158,"type":"ITEM_PURCHASED","timestamp":893425},{"participantId":10,"itemId":1001,"type":"ITEM_DESTROYED","timestamp":893425},{"participantId":9,"itemId":3114,"type":"ITEM_PURCHASED","timestamp":898842}],"timestamp":900175},{"participantFrames":{"1":{"participantId":4,"minionsKilled":86,"teamScore":0,"dominionScore":0,"totalGold":3963,"level":8,"xp":5023,"currentGold":688,"position":{"x":1259,"y":7030},"jungleMinionsKilled":0},"2":{"participantId":5,"minionsKilled":10,"teamScore":0,"dominionScore":0,"totalGold":5832,"level":10,"xp":6569,"currentGold":607,"position":{"x":6624,"y":1708},"jungleMinionsKilled":90},"3":{"participantId":3,"minionsKilled":102,"teamScore":0,"dominionScore":0,"totalGold":4841,"level":9,"xp":5853,"currentGold":678,"position":{"x":5267,"y":2084},"jungleMinionsKilled":0},"4":{"participantId":2,"minionsKilled":134,"teamScore":0,"dominionScore":0,"totalGold":5356,"level":10,"xp":7232,"currentGold":956,"position":{"x":7577,"y":999},"jungleMinionsKilled":4},"5":{"participantId":1,"minionsKilled":3,"teamScore":0,"dominionScore":0,"totalGold":3221,"level":7,"xp":3385,"currentGold":146,"position":{"x":7124,"y":1708},"jungleMinionsKilled":0},"6":{"participantId":7,"minionsKilled":124,"teamScore":0,"dominionScore":0,"totalGold":7662,"level":11,"xp":8026,"currentGold":1272,"position":{"x":1241,"y":7838},"jungleMinionsKilled":8},"7":{"participantId":6,"minionsKilled":8,"teamScore":0,"dominionScore":0,"totalGold":7048,"level":10,"xp":6565,"currentGold":198,"position":{"x":8953,"y":3928},"jungleMinionsKilled":82},"8":{"participantId":10,"minionsKilled":125,"teamScore":0,"dominionScore":0,"totalGold":7303,"level":11,"xp":7650,"currentGold":453,"position":{"x":6054,"y":4229},"jungleMinionsKilled":4},"9":{"participantId":8,"minionsKilled":128,"teamScore":0,"dominionScore":0,"totalGold":6146,"level":10,"xp":6445,"currentGold":246,"position":{"x":9152,"y":2058},"jungleMinionsKilled":0},"10":{"participantId":9,"minionsKilled":3,"teamScore":0,"dominionScore":0,"totalGold":5382,"level":8,"xp":4156,"currentGold":407,"position":{"x":6987,"y":3125},"jungleMinionsKilled":4}},"events":[{"creatorId":3,"type":"WARD_PLACED","timestamp":901133,"wardType":"UNDEFINED"},{"type":"WARD_KILL","killerId":1,"timestamp":902025,"wardType":"SIGHT_WARD"},{"participantId":6,"itemId":3814,"type":"ITEM_PURCHASED","timestamp":905727},{"participantId":6,"itemId":3134,"type":"ITEM_DESTROYED","timestamp":905727},{"participantId":6,"itemId":1028,"type":"ITEM_DESTROYED","timestamp":905727},{"participantId":6,"itemId":3133,"type":"ITEM_PURCHASED","timestamp":910648},{"participantId":1,"itemId":3114,"type":"ITEM_PURCHASED","timestamp":913723},{"participantId":1,"itemId":1004,"type":"ITEM_DESTROYED","timestamp":913723},{"participantId":1,"itemId":1004,"type":"ITEM_DESTROYED","timestamp":913723},{"creatorId":7,"type":"WARD_PLACED","timestamp":918614,"wardType":"YELLOW_TRINKET"},{"creatorId":9,"type":"WARD_PLACED","timestamp":920464,"wardType":"SIGHT_WARD"},{"participantId":5,"skillSlot":1,"type":"SKILL_LEVEL_UP","timestamp":923832,"levelUpType":"NORMAL"},{"type":"WARD_KILL","killerId":3,"timestamp":926245,"wardType":"CONTROL_WARD"},{"participantId":7,"skillSlot":4,"type":"SKILL_LEVEL_UP","timestamp":926311,"levelUpType":"NORMAL"},{"creatorId":9,"type":"WARD_PLACED","timestamp":927004,"wardType":"SIGHT_WARD"},{"participantId":10,"skillSlot":1,"type":"SKILL_LEVEL_UP","timestamp":929218,"levelUpType":"NORMAL"},{"creatorId":4,"type":"WARD_PLACED","timestamp":932588,"wardType":"YELLOW_TRINKET"},{"creatorId":1,"type":"WARD_PLACED","timestamp":934141,"wardType":"SIGHT_WARD"},{"creatorId":1,"type":"WARD_PLACED","timestamp":938766,"wardType":"SIGHT_WARD"},{"creatorId":9,"type":"WARD_PLACED","timestamp":941541,"wardType":"SIGHT_WARD"},{"type":"WARD_KILL","killerId":7,"timestamp":948313,"wardType":"YELLOW_TRINKET"},{"creatorId":3,"type":"WARD_PLACED","timestamp":948544,"wardType":"UNDEFINED"},{"participantId":9,"skillSlot":3,"type":"SKILL_LEVEL_UP","timestamp":954927,"levelUpType":"NORMAL"},{"creatorId":3,"type":"WARD_PLACED","timestamp":959391,"wardType":"YELLOW_TRINKET"}],"timestamp":960184},{"participantFrames":{"1":{"participantId":4,"minionsKilled":95,"teamScore":0,"dominionScore":0,"totalGold":4298,"level":9,"xp":5578,"currentGold":53,"position":{"x":1372,"y":3862},"jungleMinionsKilled":0},"2":{"participantId":5,"minionsKilled":13,"teamScore":0,"dominionScore":0,"totalGold":6010,"level":10,"xp":6868,"currentGold":785,"position":{"x":2526,"y":4726},"jungleMinionsKilled":90},"3":{"participantId":3,"minionsKilled":109,"teamScore":0,"dominionScore":0,"totalGold":5075,"level":10,"xp":6171,"currentGold":912,"position":{"x":3308,"y":4334},"jungleMinionsKilled":0},"4":{"participantId":2,"minionsKilled":149,"teamScore":0,"dominionScore":0,"totalGold":5865,"level":11,"xp":7900,"currentGold":1465,"position":{"x":7800,"y":860},"jungleMinionsKilled":4},"5":{"participantId":1,"minionsKilled":3,"teamScore":0,"dominionScore":0,"totalGold":3361,"level":7,"xp":3709,"currentGold":286,"position":{"x":2760,"y":4940},"jungleMinionsKilled":0},"6":{"participantId":7,"minionsKilled":133,"teamScore":0,"dominionScore":0,"totalGold":8167,"level":11,"xp":8434,"currentGold":1777,"position":{"x":1800,"y":7547},"jungleMinionsKilled":8},"7":{"participantId":6,"minionsKilled":18,"teamScore":0,"dominionScore":0,"totalGold":7482,"level":11,"xp":7359,"currentGold":632,"position":{"x":3163,"y":5246},"jungleMinionsKilled":86},"8":{"participantId":10,"minionsKilled":134,"teamScore":0,"dominionScore":0,"totalGold":7757,"level":11,"xp":8190,"currentGold":907,"position":{"x":1953,"y":7530},"jungleMinionsKilled":4},"9":{"participantId":8,"minionsKilled":141,"teamScore":0,"dominionScore":0,"totalGold":6611,"level":10,"xp":7109,"currentGold":711,"position":{"x":4797,"y":5587},"jungleMinionsKilled":0},"10":{"participantId":9,"minionsKilled":3,"teamScore":0,"dominionScore":0,"totalGold":5673,"level":8,"xp":4444,"currentGold":698,"position":{"x":2501,"y":7121},"jungleMinionsKilled":4}},"events":[{"participantId":4,"skillSlot":1,"type":"SKILL_LEVEL_UP","timestamp":961307,"levelUpType":"NORMAL"},{"creatorId":2,"type":"WARD_PLACED","timestamp":961769,"wardType":"CONTROL_WARD"},{"participantId":2,"itemId":2055,"type":"ITEM_DESTROYED","timestamp":961769},{"monsterType":"DRAGON","monsterSubType":"EARTH_DRAGON","position":{"x":9866,"y":4416},"type":"ELITE_MONSTER_KILL","killerId":6,"timestamp":974820},{"creatorId":9,"type":"WARD_PLACED","timestamp":980633,"wardType":"SIGHT_WARD"},{"participantId":2,"skillSlot":4,"type":"SKILL_LEVEL_UP","timestamp":984332,"levelUpType":"NORMAL"},{"participantId":4,"itemId":2031,"type":"ITEM_SOLD","timestamp":1009210},{"participantId":4,"itemId":1036,"type":"ITEM_SOLD","timestamp":1010432},{"participantId":4,"itemId":3074,"type":"ITEM_PURCHASED","timestamp":1010928},{"participantId":4,"itemId":3077,"type":"ITEM_DESTROYED","timestamp":1010928},{"participantId":4,"itemId":1053,"type":"ITEM_DESTROYED","timestamp":1010928},{"participantId":6,"skillSlot":4,"type":"SKILL_LEVEL_UP","timestamp":1013770,"levelUpType":"NORMAL"},{"participantId":3,"skillSlot":3,"type":"SKILL_LEVEL_UP","timestamp":1018727,"levelUpType":"NORMAL"},{"laneType":"TOP_LANE","towerType":"INNER_TURRET","teamId":100,"position":{"x":1512,"y":6699},"type":"BUILDING_KILL","killerId":10,"timestamp":1018892,"assistingParticipantIds":[7,9],"buildingType":"TOWER_BUILDING"}],"timestamp":1020193},{"participantFrames":{"1":{"participantId":4,"minionsKilled":102,"teamScore":0,"dominionScore":0,"totalGold":4677,"level":9,"xp":5950,"currentGold":432,"position":{"x":2224,"y":2714},"jungleMinionsKilled":0},"2":{"participantId":5,"minionsKilled":15,"teamScore":0,"dominionScore":0,"totalGold":6165,"level":10,"xp":7048,"currentGold":940,"position":{"x":2707,"y":3221},"jungleMinionsKilled":90},"3":{"participantId":3,"minionsKilled":110,"teamScore":0,"dominionScore":0,"totalGold":5297,"level":10,"xp":6266,"currentGold":85,"position":{"x":1472,"y":3730},"jungleMinionsKilled":0},"4":{"participantId":2,"minionsKilled":159,"teamScore":0,"dominionScore":0,"totalGold":6163,"level":11,"xp":8311,"currentGold":463,"position":{"x":1997,"y":2635},"jungleMinionsKilled":4},"5":{"participantId":1,"minionsKilled":3,"teamScore":0,"dominionScore":0,"totalGold":3577,"level":8,"xp":4246,"currentGold":502,"position":{"x":2334,"y":2400},"jungleMinionsKilled":0},"6":{"participantId":7,"minionsKilled":139,"teamScore":0,"dominionScore":0,"totalGold":8705,"level":12,"xp":8951,"currentGold":415,"position":{"x":1523,"y":3647},"jungleMinionsKilled":8},"7":{"participantId":6,"minionsKilled":19,"teamScore":0,"dominionScore":0,"totalGold":7847,"level":11,"xp":7754,"currentGold":997,"position":{"x":1626,"y":3437},"jungleMinionsKilled":86},"8":{"participantId":10,"minionsKilled":146,"teamScore":0,"dominionScore":0,"totalGold":8314,"level":12,"xp":8652,"currentGold":1464,"position":{"x":1885,"y":3266},"jungleMinionsKilled":4},"9":{"participantId":8,"minionsKilled":145,"teamScore":0,"dominionScore":0,"totalGold":6980,"level":11,"xp":7494,"currentGold":1080,"position":{"x":1795,"y":3802},"jungleMinionsKilled":0},"10":{"participantId":9,"minionsKilled":3,"teamScore":0,"dominionScore":0,"totalGold":5992,"level":9,"xp":5203,"currentGold":1017,"position":{"x":1669,"y":3548},"jungleMinionsKilled":4}},"events":[{"participantId":2,"itemId":1038,"type":"ITEM_PURCHASED","timestamp":1026368},{"creatorId":3,"type":"WARD_PLACED","timestamp":1029935,"wardType":"UNDEFINED"},{"position":{"x":621,"y":4408},"type":"CHAMPION_KILL","killerId":10,"timestamp":1031522,"victimId":4,"assistingParticipantIds":[9]},{"participantId":7,"skillSlot":2,"type":"SKILL_LEVEL_UP","timestamp":1039417,"levelUpType":"NORMAL"},{"participantId":1,"skillSlot":2,"type":"SKILL_LEVEL_UP","timestamp":1041268,"levelUpType":"NORMAL"},{"participantId":3,"itemId":3285,"type":"ITEM_PURCHASED","timestamp":1043778},{"participantId":3,"itemId":3802,"type":"ITEM_DESTROYED","timestamp":1043778},{"participantId":3,"itemId":1026,"type":"ITEM_DESTROYED","timestamp":1043778},{"creatorId":3,"type":"WARD_PLACED","timestamp":1051905,"wardType":"UNDEFINED"},{"laneType":"TOP_LANE","towerType":"BASE_TURRET","teamId":100,"position":{"x":1169,"y":4287},"type":"BUILDING_KILL","killerId":10,"timestamp":1058942,"assistingParticipantIds":[6],"buildingType":"TOWER_BUILDING"},{"creatorId":3,"type":"WARD_PLACED","timestamp":1061385,"wardType":"UNDEFINED"},{"participantId":7,"itemId":3001,"type":"ITEM_PURCHASED","timestamp":1062079},{"participantId":7,"itemId":3010,"type":"ITEM_DESTROYED","timestamp":1062079},{"laneType":"MID_LANE","towerType":"UNDEFINED_TURRET","teamId":100,"position":{"x":3203,"y":3208},"type":"BUILDING_KILL","killerId":8,"timestamp":1065977,"assistingParticipantIds":[7],"buildingType":"INHIBITOR_BUILDING"},{"participantId":8,"skillSlot":4,"type":"SKILL_LEVEL_UP","timestamp":1066969,"levelUpType":"NORMAL"},{"participantId":9,"skillSlot":3,"type":"SKILL_LEVEL_UP","timestamp":1067695,"levelUpType":"NORMAL"},{"creatorId":6,"type":"WARD_PLACED","timestamp":1072785,"wardType":"YELLOW_TRINKET"},{"position":{"x":1472,"y":3730},"type":"CHAMPION_KILL","killerId":7,"timestamp":1074469,"victimId":3,"assistingParticipantIds":[6,10,9]},{"participantId":10,"skillSlot":2,"type":"SKILL_LEVEL_UP","timestamp":1075493,"levelUpType":"NORMAL"}],"timestamp":1080217},{"participantFrames":{"1":{"participantId":4,"minionsKilled":106,"teamScore":0,"dominionScore":0,"totalGold":4932,"level":10,"xp":6497,"currentGold":337,"position":{"x":8077,"y":1451},"jungleMinionsKilled":0},"2":{"participantId":5,"minionsKilled":25,"teamScore":0,"dominionScore":0,"totalGold":7210,"level":11,"xp":8236,"currentGold":85,"position":{"x":2353,"y":2988},"jungleMinionsKilled":90},"3":{"participantId":3,"minionsKilled":119,"teamScore":0,"dominionScore":0,"totalGold":5648,"level":10,"xp":6742,"currentGold":435,"position":{"x":1738,"y":4609},"jungleMinionsKilled":0},"4":{"participantId":2,"minionsKilled":159,"teamScore":0,"dominionScore":0,"totalGold":6360,"level":11,"xp":8483,"currentGold":660,"position":{"x":851,"y":3397},"jungleMinionsKilled":4},"5":{"participantId":1,"minionsKilled":3,"teamScore":0,"dominionScore":0,"totalGold":4252,"level":9,"xp":5674,"currentGold":92,"position":{"x":287,"y":483},"jungleMinionsKilled":0},"6":{"participantId":7,"minionsKilled":141,"teamScore":0,"dominionScore":0,"totalGold":8944,"level":12,"xp":9392,"currentGold":264,"position":{"x":12805,"y":11304},"jungleMinionsKilled":8},"7":{"participantId":6,"minionsKilled":21,"teamScore":0,"dominionScore":0,"totalGold":8131,"level":11,"xp":8039,"currentGold":91,"position":{"x":9425,"y":10082},"jungleMinionsKilled":86},"8":{"participantId":10,"minionsKilled":154,"teamScore":0,"dominionScore":0,"totalGold":8829,"level":12,"xp":9191,"currentGold":1979,"position":{"x":4784,"y":6077},"jungleMinionsKilled":4},"9":{"participantId":8,"minionsKilled":147,"teamScore":0,"dominionScore":0,"totalGold":7641,"level":11,"xp":8255,"currentGold":1741,"position":{"x":5359,"y":9134},"jungleMinionsKilled":4},"10":{"participantId":9,"minionsKilled":3,"teamScore":0,"dominionScore":0,"totalGold":6149,"level":9,"xp":5527,"currentGold":84,"position":{"x":11052,"y":11363},"jungleMinionsKilled":4}},"events":[{"laneType":"TOP_LANE","towerType":"UNDEFINED_TURRET","teamId":100,"position":{"x":1171,"y":3571},"type":"BUILDING_KILL","killerId":8,"timestamp":1083554,"assistingParticipantIds":[7,6,10,9],"buildingType":"INHIBITOR_BUILDING"},{"creatorId":6,"type":"WARD_PLACED","timestamp":1084148,"wardType":"YELLOW_TRINKET"},{"position":{"x":2490,"y":1056},"type":"CHAMPION_KILL","killerId":6,"timestamp":1089010,"victimId":4,"assistingParticipantIds":[10,8,9]},{"position":{"x":1182,"y":1052},"type":"CHAMPION_KILL","killerId":5,"timestamp":1094922,"victimId":7,"assistingParticipantIds":[2,1]},{"position":{"x":922,"y":1086},"type":"CHAMPION_KILL","killerId":8,"timestamp":1098456,"victimId":2,"assistingParticipantIds":[7,10]},{"participantId":5,"skillSlot":4,"type":"SKILL_LEVEL_UP","timestamp":1099216,"levelUpType":"NORMAL"},{"participantId":7,"itemId":2031,"type":"ITEM_SOLD","timestamp":1104236},{"participantId":1,"itemId":3107,"type":"ITEM_PURCHASED","timestamp":1105656},{"participantId":1,"itemId":3114,"type":"ITEM_DESTROYED","timestamp":1105656},{"participantId":1,"itemId":3801,"type":"ITEM_DESTROYED","timestamp":1105656},{"participantId":4,"itemId":1036,"type":"ITEM_PURCHASED","timestamp":1106845},{"type":"WARD_KILL","killerId":5,"timestamp":1108629,"wardType":"YELLOW_TRINKET"},{"participantId":10,"itemId":3004,"type":"ITEM_DESTROYED","timestamp":1109388},{"participantId":4,"skillSlot":3,"type":"SKILL_LEVEL_UP","timestamp":1109784,"levelUpType":"NORMAL"},{"participantId":7,"itemId":1033,"type":"ITEM_PURCHASED","timestamp":1111868},{"creatorId":8,"type":"WARD_PLACED","timestamp":1112695,"wardType":"YELLOW_TRINKET"},{"participantId":6,"itemId":3134,"type":"ITEM_PURCHASED","timestamp":1114643},{"position":{"x":4784,"y":6077},"type":"CHAMPION_KILL","killerId":1,"timestamp":1114709,"victimId":10,"assistingParticipantIds":[5]},{"participantId":6,"itemId":2031,"type":"ITEM_SOLD","timestamp":1115502},{"participantId":6,"itemId":2055,"type":"ITEM_PURCHASED","timestamp":1115799},{"participantId":6,"itemId":2055,"type":"ITEM_PURCHASED","timestamp":1115865},{"type":"WARD_KILL","killerId":5,"timestamp":1120952,"wardType":"YELLOW_TRINKET"},{"creatorId":3,"type":"WARD_PLACED","timestamp":1121745,"wardType":"UNDEFINED"},{"participantId":1,"skillSlot":3,"type":"SKILL_LEVEL_UP","timestamp":1123661,"levelUpType":"NORMAL"},{"participantId":5,"itemId":3006,"type":"ITEM_PURCHASED","timestamp":1127228},{"participantId":5,"itemId":1001,"type":"ITEM_DESTROYED","timestamp":1127228},{"participantId":9,"itemId":2031,"type":"ITEM_SOLD","timestamp":1128782},{"participantId":5,"itemId":3134,"type":"ITEM_PURCHASED","timestamp":1128848},{"participantId":5,"itemId":1036,"type":"ITEM_DESTROYED","timestamp":1128848},{"participantId":5,"itemId":1036,"type":"ITEM_PURCHASED","timestamp":1129046},{"participantId":9,"itemId":3801,"type":"ITEM_PURCHASED","timestamp":1130796},{"participantId":9,"itemId":2139,"type":"ITEM_PURCHASED","timestamp":1132414},{"participantId":9,"itemId":2139,"type":"ITEM_DESTROYED","timestamp":1132414},{"participantId":1,"itemId":1052,"type":"ITEM_PURCHASED","timestamp":1139091}],"timestamp":1140221},{"participantFrames":{"1":{"participantId":4,"minionsKilled":111,"teamScore":0,"dominionScore":0,"totalGold":5145,"level":10,"xp":6899,"currentGold":550,"position":{"x":11975,"y":2348},"jungleMinionsKilled":0},"2":{"participantId":5,"minionsKilled":30,"teamScore":0,"dominionScore":0,"totalGold":7643,"level":12,"xp":8852,"currentGold":518,"position":{"x":12546,"y":2578},"jungleMinionsKilled":98},"3":{"participantId":3,"minionsKilled":131,"teamScore":0,"dominionScore":0,"totalGold":6118,"level":11,"xp":7464,"currentGold":56,"position":{"x":1026,"y":2012},"jungleMinionsKilled":0},"4":{"participantId":2,"minionsKilled":166,"teamScore":0,"dominionScore":0,"totalGold":6609,"level":12,"xp":8842,"currentGold":109,"position":{"x":2007,"y":1599},"jungleMinionsKilled":4},"5":{"participantId":1,"minionsKilled":3,"teamScore":0,"dominionScore":0,"totalGold":4408,"level":9,"xp":6054,"currentGold":248,"position":{"x":11747,"y":1961},"jungleMinionsKilled":0},"6":{"participantId":7,"minionsKilled":149,"teamScore":0,"dominionScore":0,"totalGold":9383,"level":13,"xp":10132,"currentGold":704,"position":{"x":12033,"y":2641},"jungleMinionsKilled":12},"7":{"participantId":6,"minionsKilled":21,"teamScore":0,"dominionScore":0,"totalGold":8624,"level":12,"xp":8904,"currentGold":584,"position":{"x":2228,"y":2698},"jungleMinionsKilled":102},"8":{"participantId":10,"minionsKilled":159,"teamScore":0,"dominionScore":0,"totalGold":9035,"level":12,"xp":9360,"currentGold":235,"position":{"x":1973,"y":2901},"jungleMinionsKilled":4},"9":{"participantId":8,"minionsKilled":147,"teamScore":0,"dominionScore":0,"totalGold":7763,"level":11,"xp":8255,"currentGold":113,"position":{"x":2427,"y":2483},"jungleMinionsKilled":4},"10":{"participantId":9,"minionsKilled":3,"teamScore":0,"dominionScore":0,"totalGold":6289,"level":9,"xp":5696,"currentGold":224,"position":{"x":1820,"y":3348},"jungleMinionsKilled":4}},"events":[{"participantId":10,"itemId":3077,"type":"ITEM_PURCHASED","timestamp":1140287},{"participantId":10,"beforeId":3077,"afterId":0,"type":"ITEM_UNDO","timestamp":1141675},{"participantId":8,"itemId":3151,"type":"ITEM_PURCHASED","timestamp":1141873},{"participantId":8,"itemId":3136,"type":"ITEM_DESTROYED","timestamp":1141873},{"participantId":8,"itemId":2055,"type":"ITEM_PURCHASED","timestamp":1143029},{"participantId":8,"itemId":2055,"type":"ITEM_PURCHASED","timestamp":1144747},{"creatorId":3,"type":"WARD_PLACED","timestamp":1145012,"wardType":"UNDEFINED"},{"participantId":8,"itemId":3363,"type":"ITEM_PURCHASED","timestamp":1145342},{"participantId":8,"itemId":3340,"type":"ITEM_DESTROYED","timestamp":1145342},{"participantId":10,"itemId":3134,"type":"ITEM_PURCHASED","timestamp":1145805},{"participantId":10,"itemId":1036,"type":"ITEM_PURCHASED","timestamp":1146632},{"creatorId":4,"type":"WARD_PLACED","timestamp":1148515,"wardType":"YELLOW_TRINKET"},{"participantId":2,"skillSlot":2,"type":"SKILL_LEVEL_UP","timestamp":1154957,"levelUpType":"NORMAL"},{"participantId":10,"itemId":2140,"type":"ITEM_PURCHASED","timestamp":1155452},{"participantId":10,"itemId":2140,"type":"ITEM_DESTROYED","timestamp":1155452},{"creatorId":9,"type":"WARD_PLACED","timestamp":1158658,"wardType":"SIGHT_WARD"},{"creatorId":9,"type":"WARD_PLACED","timestamp":1160837,"wardType":"SIGHT_WARD"},{"creatorId":1,"type":"WARD_PLACED","timestamp":1169559,"wardType":"SIGHT_WARD"},{"creatorId":1,"type":"WARD_PLACED","timestamp":1173523,"wardType":"SIGHT_WARD"},{"participantId":2,"itemId":1018,"type":"ITEM_PURCHASED","timestamp":1174019},{"creatorId":1,"type":"WARD_PLACED","timestamp":1176068,"wardType":"SIGHT_WARD"},{"participantId":3,"skillSlot":4,"type":"SKILL_LEVEL_UP","timestamp":1176597,"levelUpType":"NORMAL"},{"monsterType":"RIFTHERALD","position":{"x":5200,"y":10454},"type":"ELITE_MONSTER_KILL","killerId":6,"timestamp":1177059},{"participantId":6,"itemId":3340,"type":"ITEM_DESTROYED","timestamp":1178645},{"participantId":6,"skillSlot":2,"type":"SKILL_LEVEL_UP","timestamp":1179305,"levelUpType":"NORMAL"},{"participantId":7,"itemId":3379,"type":"ITEM_PURCHASED","timestamp":1183400},{"participantId":7,"itemId":3373,"type":"ITEM_PURCHASED","timestamp":1183400},{"participantId":7,"itemId":3001,"type":"ITEM_DESTROYED","timestamp":1183400},{"participantId":7,"itemId":3068,"type":"ITEM_DESTROYED","timestamp":1183400},{"participantId":7,"skillSlot":2,"type":"SKILL_LEVEL_UP","timestamp":1184787,"levelUpType":"NORMAL"},{"participantId":5,"skillSlot":1,"type":"SKILL_LEVEL_UP","timestamp":1184985,"levelUpType":"NORMAL"},{"participantId":3,"itemId":1026,"type":"ITEM_PURCHASED","timestamp":1186274},{"participantId":3,"itemId":3363,"type":"ITEM_PURCHASED","timestamp":1186902},{"participantId":3,"itemId":3340,"type":"ITEM_DESTROYED","timestamp":1186902},{"creatorId":9,"type":"WARD_PLACED","timestamp":1190008,"wardType":"SIGHT_WARD"},{"creatorId":3,"type":"WARD_PLACED","timestamp":1194368,"wardType":"UNDEFINED"},{"participantId":6,"itemId":3513,"type":"ITEM_DESTROYED","timestamp":1199359}],"timestamp":1200251},{"participantFrames":{"1":{"participantId":4,"minionsKilled":111,"totalGold":5821,"level":11,"xp":7583,"currentGold":921,"jungleMinionsKilled":0},"2":{"participantId":5,"minionsKilled":34,"totalGold":7869,"level":12,"xp":9568,"currentGold":744,"jungleMinionsKilled":98},"3":{"participantId":3,"minionsKilled":131,"totalGold":6244,"level":11,"xp":7685,"currentGold":94,"jungleMinionsKilled":0},"4":{"participantId":2,"minionsKilled":169,"totalGold":6816,"level":12,"xp":9118,"currentGold":316,"jungleMinionsKilled":4},"5":{"participantId":1,"minionsKilled":4,"totalGold":4678,"level":10,"xp":6694,"currentGold":518,"jungleMinionsKilled":0},"6":{"participantId":7,"minionsKilled":149,"totalGold":9559,"level":13,"xp":10132,"currentGold":109,"jungleMinionsKilled":12},"7":{"participantId":6,"minionsKilled":25,"totalGold":8936,"level":12,"xp":9292,"currentGold":836,"jungleMinionsKilled":102},"8":{"participantId":10,"minionsKilled":161,"totalGold":9239,"level":12,"xp":9583,"currentGold":439,"jungleMinionsKilled":4},"9":{"participantId":8,"minionsKilled":152,"totalGold":8099,"level":11,"xp":8491,"currentGold":449,"jungleMinionsKilled":4},"10":{"participantId":9,"minionsKilled":4,"totalGold":6490,"level":9,"xp":6068,"currentGold":365,"jungleMinionsKilled":4}},"events":[{"laneType":"MID_LANE","towerType":"NEXUS_TURRET","teamId":100,"position":{"x":1748,"y":2270},"type":"BUILDING_KILL","killerId":10,"timestamp":1201968,"assistingParticipantIds":[6,8],"buildingType":"TOWER_BUILDING"},{"position":{"x":12009,"y":2697},"type":"CHAMPION_KILL","killerId":4,"timestamp":1202067,"victimId":7,"assistingParticipantIds":[5,1]},{"participantId":7,"itemId":3105,"type":"ITEM_PURCHASED","timestamp":1206329},{"participantId":7,"itemId":1033,"type":"ITEM_DESTROYED","timestamp":1206329},{"creatorId":3,"type":"WARD_PLACED","timestamp":1207320,"wardType":"UNDEFINED"},{"laneType":"MID_LANE","towerType":"NEXUS_TURRET","teamId":100,"position":{"x":2177,"y":1807},"type":"BUILDING_KILL","killerId":6,"timestamp":1209601,"assistingParticipantIds":[10,8,9],"buildingType":"TOWER_BUILDING"},{"participantId":4,"skillSlot":4,"type":"SKILL_LEVEL_UP","timestamp":1209700,"levelUpType":"NORMAL"},{"creatorId":3,"type":"WARD_PLACED","timestamp":1215020,"wardType":"UNDEFINED"},{"participantId":1,"skillSlot":2,"type":"SKILL_LEVEL_UP","timestamp":1215251,"levelUpType":"NORMAL"},{"creatorId":3,"type":"WARD_PLACED","timestamp":1225096,"wardType":"UNDEFINED"},{"position":{"x":2138,"y":885},"type":"CHAMPION_KILL","killerId":4,"timestamp":1228565,"victimId":10,"assistingParticipantIds":[5,3,1]}],"timestamp":1260251}],"frameInterval":60000}